<?xml version="1.0" encoding="utf-8"?>
<abapGit version="v1.0.0" serializer="ZCL_ABAPGIT_OBJECT_BY_SOBJ" serializer_version="1.0">
 <asx:abap xmlns:asx="http://www.sap.com/abapxml" version="1.0">
  <asx:values>
   <CWBCIHEAD>
    <CWBCIHEAD>
     <INSTA>0020751259</INSTA>
     <PAKID>6</PAKID>
     <ALEID>0000589747</ALEID>
     <VERSNO>0002</VERSNO>
     <FORMAT_ID>3</FORMAT_ID>
    </CWBCIHEAD>
   </CWBCIHEAD>
   <CWBCIHEAD_field_catalog>
    <item>
     <POS>1</POS>
     <NAME>INSTA</NAME>
     <TYPE_KIND>C</TYPE_KIND>
     <LENGTH>10</LENGTH>
     <IS_KEY>X</IS_KEY>
    </item>
    <item>
     <POS>2</POS>
     <NAME>PAKID</NAME>
     <TYPE_KIND>C</TYPE_KIND>
     <LENGTH>10</LENGTH>
     <IS_KEY>X</IS_KEY>
    </item>
    <item>
     <POS>3</POS>
     <NAME>ALEID</NAME>
     <TYPE_KIND>N</TYPE_KIND>
     <LENGTH>10</LENGTH>
     <IS_KEY>X</IS_KEY>
    </item>
    <item>
     <POS>4</POS>
     <NAME>VERSNO</NAME>
     <TYPE_KIND>N</TYPE_KIND>
     <LENGTH>4</LENGTH>
     <IS_KEY>X</IS_KEY>
    </item>
    <item>
     <POS>5</POS>
     <NAME>FORMAT_ID</NAME>
     <TYPE_KIND>I</TYPE_KIND>
     <LENGTH>10</LENGTH>
    </item>
    <item>
     <POS>6</POS>
     <NAME>INCOMPLETE</NAME>
     <TYPE_KIND>C</TYPE_KIND>
     <LENGTH>1</LENGTH>
    </item>
    <item>
     <POS>7</POS>
     <NAME>MANUAL_ACTIVITY</NAME>
     <TYPE_KIND>C</TYPE_KIND>
     <LENGTH>1</LENGTH>
    </item>
    <item>
     <POS>8</POS>
     <NAME>IS_TRANSPORTABLE</NAME>
     <TYPE_KIND>C</TYPE_KIND>
     <LENGTH>1</LENGTH>
    </item>
   </CWBCIHEAD_field_catalog>
   <CWBCIDATA_field_catalog>
    <item>
     <POS>1</POS>
     <NAME>RELID</NAME>
     <TYPE_KIND>C</TYPE_KIND>
     <LENGTH>2</LENGTH>
     <IS_KEY>X</IS_KEY>
    </item>
    <item>
     <POS>2</POS>
     <NAME>INSTA</NAME>
     <TYPE_KIND>C</TYPE_KIND>
     <LENGTH>10</LENGTH>
     <IS_KEY>X</IS_KEY>
    </item>
    <item>
     <POS>3</POS>
     <NAME>PAKID</NAME>
     <TYPE_KIND>C</TYPE_KIND>
     <LENGTH>10</LENGTH>
     <IS_KEY>X</IS_KEY>
    </item>
    <item>
     <POS>4</POS>
     <NAME>ALEID</NAME>
     <TYPE_KIND>N</TYPE_KIND>
     <LENGTH>10</LENGTH>
     <IS_KEY>X</IS_KEY>
    </item>
    <item>
     <POS>5</POS>
     <NAME>VERSNO</NAME>
     <TYPE_KIND>N</TYPE_KIND>
     <LENGTH>4</LENGTH>
     <IS_KEY>X</IS_KEY>
    </item>
    <item>
     <POS>6</POS>
     <NAME>SRTF2</NAME>
     <TYPE_KIND>I</TYPE_KIND>
     <LENGTH>10</LENGTH>
     <IS_KEY>X</IS_KEY>
    </item>
    <item>
     <POS>7</POS>
     <NAME>CLUSTR</NAME>
     <TYPE_KIND>s</TYPE_KIND>
     <LENGTH>5</LENGTH>
    </item>
    <item>
     <POS>8</POS>
     <NAME>CLUSTD</NAME>
     <TYPE_KIND>X</TYPE_KIND>
     <LENGTH>2886</LENGTH>
    </item>
   </CWBCIDATA_field_catalog>
   <CWBCIDPNDC>
    <CWBCIDPNDC>
     <INSTA>0020751259</INSTA>
     <PAKID>6</PAKID>
     <ALEID>0000589747</ALEID>
     <VERSNO>0002</VERSNO>
     <DEPTYPE>P</DEPTYPE>
     <CIINSTA_D>0020751259</CIINSTA_D>
     <CIPAKID_D>6</CIPAKID_D>
     <CIALEID_D>0000019964</CIALEID_D>
     <NTNUMM_D>0002286247</NTNUMM_D>
    </CWBCIDPNDC>
    <CWBCIDPNDC>
     <INSTA>0020751259</INSTA>
     <PAKID>6</PAKID>
     <ALEID>0000589747</ALEID>
     <VERSNO>0002</VERSNO>
     <DEPTYPE>P</DEPTYPE>
     <CIINSTA_D>0020751259</CIINSTA_D>
     <CIPAKID_D>6</CIPAKID_D>
     <CIALEID_D>0000088713</CIALEID_D>
     <NTNUMM_D>0002363748</NTNUMM_D>
    </CWBCIDPNDC>
    <CWBCIDPNDC>
     <INSTA>0020751259</INSTA>
     <PAKID>6</PAKID>
     <ALEID>0000589747</ALEID>
     <VERSNO>0002</VERSNO>
     <DEPTYPE>P</DEPTYPE>
     <CIINSTA_D>0020751259</CIINSTA_D>
     <CIPAKID_D>6</CIPAKID_D>
     <CIALEID_D>0000191063</CIALEID_D>
     <NTNUMM_D>0002463781</NTNUMM_D>
    </CWBCIDPNDC>
   </CWBCIDPNDC>
   <CWBCIDPNDC_field_catalog>
    <item>
     <POS>1</POS>
     <NAME>INSTA</NAME>
     <TYPE_KIND>C</TYPE_KIND>
     <LENGTH>10</LENGTH>
     <IS_KEY>X</IS_KEY>
    </item>
    <item>
     <POS>2</POS>
     <NAME>PAKID</NAME>
     <TYPE_KIND>C</TYPE_KIND>
     <LENGTH>10</LENGTH>
     <IS_KEY>X</IS_KEY>
    </item>
    <item>
     <POS>3</POS>
     <NAME>ALEID</NAME>
     <TYPE_KIND>N</TYPE_KIND>
     <LENGTH>10</LENGTH>
     <IS_KEY>X</IS_KEY>
    </item>
    <item>
     <POS>4</POS>
     <NAME>VERSNO</NAME>
     <TYPE_KIND>N</TYPE_KIND>
     <LENGTH>4</LENGTH>
     <IS_KEY>X</IS_KEY>
    </item>
    <item>
     <POS>5</POS>
     <NAME>DEPTYPE</NAME>
     <TYPE_KIND>C</TYPE_KIND>
     <LENGTH>1</LENGTH>
     <IS_KEY>X</IS_KEY>
    </item>
    <item>
     <POS>6</POS>
     <NAME>CIINSTA_D</NAME>
     <TYPE_KIND>C</TYPE_KIND>
     <LENGTH>10</LENGTH>
     <IS_KEY>X</IS_KEY>
    </item>
    <item>
     <POS>7</POS>
     <NAME>CIPAKID_D</NAME>
     <TYPE_KIND>C</TYPE_KIND>
     <LENGTH>10</LENGTH>
     <IS_KEY>X</IS_KEY>
    </item>
    <item>
     <POS>8</POS>
     <NAME>CIALEID_D</NAME>
     <TYPE_KIND>N</TYPE_KIND>
     <LENGTH>10</LENGTH>
     <IS_KEY>X</IS_KEY>
    </item>
    <item>
     <POS>9</POS>
     <NAME>NTNUMM_D</NAME>
     <TYPE_KIND>N</TYPE_KIND>
     <LENGTH>10</LENGTH>
     <IS_KEY>X</IS_KEY>
    </item>
   </CWBCIDPNDC_field_catalog>
   <CWBCIFIXED_field_catalog>
    <item>
     <POS>1</POS>
     <NAME>INSTA</NAME>
     <TYPE_KIND>C</TYPE_KIND>
     <LENGTH>10</LENGTH>
     <IS_KEY>X</IS_KEY>
    </item>
    <item>
     <POS>2</POS>
     <NAME>PAKID</NAME>
     <TYPE_KIND>C</TYPE_KIND>
     <LENGTH>10</LENGTH>
     <IS_KEY>X</IS_KEY>
    </item>
    <item>
     <POS>3</POS>
     <NAME>ALEID</NAME>
     <TYPE_KIND>N</TYPE_KIND>
     <LENGTH>10</LENGTH>
     <IS_KEY>X</IS_KEY>
    </item>
    <item>
     <POS>4</POS>
     <NAME>VERSNO</NAME>
     <TYPE_KIND>N</TYPE_KIND>
     <LENGTH>4</LENGTH>
     <IS_KEY>X</IS_KEY>
    </item>
    <item>
     <POS>5</POS>
     <NAME>DEPAKID_F</NAME>
     <TYPE_KIND>C</TYPE_KIND>
     <LENGTH>10</LENGTH>
     <IS_KEY>X</IS_KEY>
    </item>
    <item>
     <POS>6</POS>
     <NAME>DEALEID_F</NAME>
     <TYPE_KIND>N</TYPE_KIND>
     <LENGTH>10</LENGTH>
     <IS_KEY>X</IS_KEY>
    </item>
   </CWBCIFIXED_field_catalog>
   <CWBCIVALID>
    <CWBCIVALID>
     <INSTA>0020751259</INSTA>
     <PAKID>6</PAKID>
     <ALEID>0000589747</ALEID>
     <VERSNO>0002</VERSNO>
     <TRPAKID>6</TRPAKID>
     <TRTYPEID>P</TRTYPEID>
     <TRALSID>000051</TRALSID>
     <DEPAKID_LO>6</DEPAKID_LO>
     <DEALEID_LO>0000000503</DEALEID_LO>
     <DEPAKID_HI>6</DEPAKID_HI>
     <DEALEID_HI>0000000722</DEALEID_HI>
    </CWBCIVALID>
   </CWBCIVALID>
   <CWBCIVALID_field_catalog>
    <item>
     <POS>1</POS>
     <NAME>INSTA</NAME>
     <TYPE_KIND>C</TYPE_KIND>
     <LENGTH>10</LENGTH>
     <IS_KEY>X</IS_KEY>
    </item>
    <item>
     <POS>2</POS>
     <NAME>PAKID</NAME>
     <TYPE_KIND>C</TYPE_KIND>
     <LENGTH>10</LENGTH>
     <IS_KEY>X</IS_KEY>
    </item>
    <item>
     <POS>3</POS>
     <NAME>ALEID</NAME>
     <TYPE_KIND>N</TYPE_KIND>
     <LENGTH>10</LENGTH>
     <IS_KEY>X</IS_KEY>
    </item>
    <item>
     <POS>4</POS>
     <NAME>VERSNO</NAME>
     <TYPE_KIND>N</TYPE_KIND>
     <LENGTH>4</LENGTH>
     <IS_KEY>X</IS_KEY>
    </item>
    <item>
     <POS>5</POS>
     <NAME>TRPAKID</NAME>
     <TYPE_KIND>C</TYPE_KIND>
     <LENGTH>10</LENGTH>
     <IS_KEY>X</IS_KEY>
    </item>
    <item>
     <POS>6</POS>
     <NAME>TRTYPEID</NAME>
     <TYPE_KIND>C</TYPE_KIND>
     <LENGTH>1</LENGTH>
     <IS_KEY>X</IS_KEY>
    </item>
    <item>
     <POS>7</POS>
     <NAME>TRALSID</NAME>
     <TYPE_KIND>N</TYPE_KIND>
     <LENGTH>6</LENGTH>
     <IS_KEY>X</IS_KEY>
    </item>
    <item>
     <POS>8</POS>
     <NAME>DEPAKID_LO</NAME>
     <TYPE_KIND>C</TYPE_KIND>
     <LENGTH>10</LENGTH>
     <IS_KEY>X</IS_KEY>
    </item>
    <item>
     <POS>9</POS>
     <NAME>DEALEID_LO</NAME>
     <TYPE_KIND>N</TYPE_KIND>
     <LENGTH>10</LENGTH>
     <IS_KEY>X</IS_KEY>
    </item>
    <item>
     <POS>10</POS>
     <NAME>DEPAKID_HI</NAME>
     <TYPE_KIND>C</TYPE_KIND>
     <LENGTH>10</LENGTH>
     <IS_KEY>X</IS_KEY>
    </item>
    <item>
     <POS>11</POS>
     <NAME>DEALEID_HI</NAME>
     <TYPE_KIND>N</TYPE_KIND>
     <LENGTH>10</LENGTH>
     <IS_KEY>X</IS_KEY>
    </item>
   </CWBCIVALID_field_catalog>
   <CWBCIOBJ>
    <CWBCIOBJ>
     <INSTA>0020751259</INSTA>
     <PAKID>6</PAKID>
     <ALEID>0000589747</ALEID>
     <VERSNO>0002</VERSNO>
     <PGMID>LIMU</PGMID>
     <OBJECT>FUNC</OBJECT>
     <OBJ_NAME>ISHMED_QUIT_SERVICE</OBJ_NAME>
     <TRPGMID>R3TR</TRPGMID>
     <TROBJECT>FUGR</TROBJECT>
     <TROBJ_NAME>N1LO</TROBJ_NAME>
    </CWBCIOBJ>
   </CWBCIOBJ>
   <CWBCIOBJ_field_catalog>
    <item>
     <POS>1</POS>
     <NAME>INSTA</NAME>
     <TYPE_KIND>C</TYPE_KIND>
     <LENGTH>10</LENGTH>
     <IS_KEY>X</IS_KEY>
    </item>
    <item>
     <POS>2</POS>
     <NAME>PAKID</NAME>
     <TYPE_KIND>C</TYPE_KIND>
     <LENGTH>10</LENGTH>
     <IS_KEY>X</IS_KEY>
    </item>
    <item>
     <POS>3</POS>
     <NAME>ALEID</NAME>
     <TYPE_KIND>N</TYPE_KIND>
     <LENGTH>10</LENGTH>
     <IS_KEY>X</IS_KEY>
    </item>
    <item>
     <POS>4</POS>
     <NAME>VERSNO</NAME>
     <TYPE_KIND>N</TYPE_KIND>
     <LENGTH>4</LENGTH>
     <IS_KEY>X</IS_KEY>
    </item>
    <item>
     <POS>5</POS>
     <NAME>PGMID</NAME>
     <TYPE_KIND>C</TYPE_KIND>
     <LENGTH>4</LENGTH>
     <IS_KEY>X</IS_KEY>
    </item>
    <item>
     <POS>6</POS>
     <NAME>OBJECT</NAME>
     <TYPE_KIND>C</TYPE_KIND>
     <LENGTH>4</LENGTH>
     <IS_KEY>X</IS_KEY>
    </item>
    <item>
     <POS>7</POS>
     <NAME>OBJ_NAME</NAME>
     <TYPE_KIND>C</TYPE_KIND>
     <LENGTH>120</LENGTH>
     <IS_KEY>X</IS_KEY>
    </item>
    <item>
     <POS>8</POS>
     <NAME>TRPGMID</NAME>
     <TYPE_KIND>C</TYPE_KIND>
     <LENGTH>4</LENGTH>
    </item>
    <item>
     <POS>9</POS>
     <NAME>TROBJECT</NAME>
     <TYPE_KIND>C</TYPE_KIND>
     <LENGTH>4</LENGTH>
    </item>
    <item>
     <POS>10</POS>
     <NAME>TROBJ_NAME</NAME>
     <TYPE_KIND>C</TYPE_KIND>
     <LENGTH>40</LENGTH>
    </item>
   </CWBCIOBJ_field_catalog>
   <CWBCICATTR_field_catalog>
    <item>
     <POS>1</POS>
     <NAME>INSTA</NAME>
     <TYPE_KIND>C</TYPE_KIND>
     <LENGTH>10</LENGTH>
     <IS_KEY>X</IS_KEY>
    </item>
    <item>
     <POS>2</POS>
     <NAME>PAKID</NAME>
     <TYPE_KIND>C</TYPE_KIND>
     <LENGTH>10</LENGTH>
     <IS_KEY>X</IS_KEY>
    </item>
    <item>
     <POS>3</POS>
     <NAME>ALEID</NAME>
     <TYPE_KIND>N</TYPE_KIND>
     <LENGTH>10</LENGTH>
     <IS_KEY>X</IS_KEY>
    </item>
    <item>
     <POS>4</POS>
     <NAME>VERSNO</NAME>
     <TYPE_KIND>N</TYPE_KIND>
     <LENGTH>4</LENGTH>
     <IS_KEY>X</IS_KEY>
    </item>
    <item>
     <POS>5</POS>
     <NAME>CONFIRMED</NAME>
     <TYPE_KIND>C</TYPE_KIND>
     <LENGTH>1</LENGTH>
    </item>
    <item>
     <POS>6</POS>
     <NAME>CISTATUS</NAME>
     <TYPE_KIND>C</TYPE_KIND>
     <LENGTH>1</LENGTH>
    </item>
    <item>
     <POS>7</POS>
     <NAME>CONFIRM_ACTIVITY</NAME>
     <TYPE_KIND>C</TYPE_KIND>
     <LENGTH>1</LENGTH>
    </item>
   </CWBCICATTR_field_catalog>
   <CWBCIINVLD_field_catalog>
    <item>
     <POS>1</POS>
     <NAME>INSTA</NAME>
     <TYPE_KIND>C</TYPE_KIND>
     <LENGTH>10</LENGTH>
     <IS_KEY>X</IS_KEY>
    </item>
    <item>
     <POS>2</POS>
     <NAME>PAKID</NAME>
     <TYPE_KIND>C</TYPE_KIND>
     <LENGTH>10</LENGTH>
     <IS_KEY>X</IS_KEY>
    </item>
    <item>
     <POS>3</POS>
     <NAME>ALEID</NAME>
     <TYPE_KIND>N</TYPE_KIND>
     <LENGTH>10</LENGTH>
     <IS_KEY>X</IS_KEY>
    </item>
    <item>
     <POS>4</POS>
     <NAME>VERSNO</NAME>
     <TYPE_KIND>N</TYPE_KIND>
     <LENGTH>4</LENGTH>
     <IS_KEY>X</IS_KEY>
    </item>
    <item>
     <POS>5</POS>
     <NAME>TRPAKID</NAME>
     <TYPE_KIND>C</TYPE_KIND>
     <LENGTH>10</LENGTH>
     <IS_KEY>X</IS_KEY>
    </item>
    <item>
     <POS>6</POS>
     <NAME>TRTYPEID</NAME>
     <TYPE_KIND>C</TYPE_KIND>
     <LENGTH>1</LENGTH>
     <IS_KEY>X</IS_KEY>
    </item>
    <item>
     <POS>7</POS>
     <NAME>TRALSID</NAME>
     <TYPE_KIND>N</TYPE_KIND>
     <LENGTH>6</LENGTH>
     <IS_KEY>X</IS_KEY>
    </item>
    <item>
     <POS>8</POS>
     <NAME>DEPAKID_LO</NAME>
     <TYPE_KIND>C</TYPE_KIND>
     <LENGTH>10</LENGTH>
     <IS_KEY>X</IS_KEY>
    </item>
    <item>
     <POS>9</POS>
     <NAME>DEALEID_LO</NAME>
     <TYPE_KIND>N</TYPE_KIND>
     <LENGTH>10</LENGTH>
     <IS_KEY>X</IS_KEY>
    </item>
    <item>
     <POS>10</POS>
     <NAME>DEPAKID_HI</NAME>
     <TYPE_KIND>C</TYPE_KIND>
     <LENGTH>10</LENGTH>
     <IS_KEY>X</IS_KEY>
    </item>
    <item>
     <POS>11</POS>
     <NAME>DEALEID_HI</NAME>
     <TYPE_KIND>N</TYPE_KIND>
     <LENGTH>10</LENGTH>
     <IS_KEY>X</IS_KEY>
    </item>
   </CWBCIINVLD_field_catalog>
   <CWBCIDATAOBJ>
    <CWBCIDATAOBJ>
     <RELID>CI</RELID>
     <INSTA>0020751259</INSTA>
     <PAKID>6</PAKID>
     <ALEID>0000589747</ALEID>
     <VERSNO>0002</VERSNO>
     <PGMID>LIMU</PGMID>
     <OBJTYPE>FUNC</OBJTYPE>
     <OBJNAME>ISHMED_QUIT_SERVICE</OBJNAME>
     <OBJVERSNO>99989</OBJVERSNO>
     <DELTA_MODE>O</DELTA_MODE>
     <CLUSTR>2685</CLUSTR>
     <CLUSTD>/wYCAQICgAA0MTAzAAAAAPtYAAASH50C2r31NTeKHHE/XFXuA+QDENdVvJecjGR7d+8cli0Eg0yM
gB1Gis4vFLLHNmUZuQCtd/fL5CUf4972LcmHSs8AktdGFkIOPqPy7vQMM9D9m56e7vnzhz9uwe97
9t93WwU/bUvZIvDv31tbo/9K7z9dT4SPNIqDafhuu7Pb3hZoeDo9C8KLd9uz5Lz18/Z7WfLjT4f+
2L+5VxPahvEhPHy3fZkkN4eieHt7uxv7N7un02uRNYAa22nzj/5kRmNZGrX6pjfSFKLIktJVHIJG
RJQlzbBUE1JkmbomS8MRJwwMJHZ1U+nBM31gqZbSR7LhHvWR5n0YGMRzER4aKpLE+VNJwUiRrY5p
SyInJUUlxhDJI8inlNRDFsIKQRp7LUYI+EFyG34t/gdvywulnml3Fcaaaaueg40h43JEkNWRNUnM
qLRkT+5kJXtZyX5e+SAnXgMh3hFPzCRm7BMmeE7MxXYdrLjsWylRGgZHwZAShGXkIYxtLImLIunY
sDTZkUSeSkOEXcO2GAQgQp6TXNY7sk4vJzS6ppOzWXhBQ2CEFzMx/r9c66qtocpcz8KrBHQ1Bm2m
QuvPF8nf6uO8BxlSlfMPsyBJAhrR8IxGQj9I/GhMg4RGdfGvK6bpgbofI+2hDKNy6PuTiRDEiTAG
OYIkFi5ofEOjKKlLBgN7yBoa2Lb6yKrcFSj8GETT8JqG9THuMSNlW1VZVrjWCzv6DgB/Qcc0FERh
B+1E4yhgw7feoWB4KlOmvlK5C/o+aH7gT/zZeTQ7F2gE1DgRbEu0db1OMXBlU+ScT+gFnVAYD2BB
a+TZtF3kddE/qjLepbf0ght9wR/Hp5eTgH79J2RS8GvXJLvfNyrrkTq9vg4S4a9C/Dk8vYRBTYUh
jcaz00sQ8JkkQoaFjcq2KQij4PSyXpV6OkdCiOlkzCeISx8mukltfoXh9cCzG/SrStH7+tskCS6u
2LR25iez6xoZdzZwK4Z9RXhlzSLhIhXgJ+GWhqFgeJbtObYzcIR3ws5o58f6xDGR4RJPqz43mJlJ
TftB8CexMJyCszThVqvu0ZyKQ4zKmjUX5wvo1h1pdoVXbkAvqXAHsjq7CTxBjyjdysOe+YLc+5tP
HfUxnyt3VeZt61BwpjezG2EWgiNyFn397fSqfi/Kxj1DqyxDdGGc/QQuOJvIzwIq8LhCgYIbEOc8
EW6D6KxuiVxliJiLXlUodwpadebHwh0fnUUZMCXSCESCvqLh+5rl2WCUaODnhkJwLehdNli4GM/l
ablEIZ5i6XblICQ8nwL+ETNmcQLGORb88MaP42dzHomCDX1jw3zlJ/5kWvvMQgxioupeVxiD5UqC
hE7qY/nEJr9WNronM9CekAGefL4RXp3A3G5Spjs+KBIzXhZxTv5U2xRokyOEl7m+5dZDwFkXUveX
r4pAMHtBk4gmdc8kGCnaZpJkUoxpkHcK65A8UqxLjnT2eCo53Lm9fRZZfnU3E8X9DAP8upVJ9OrL
bncuFve5zmgsMCeMxrUNGTZ9HCMM7mpVG9CjX//FFkATKijhFY3y5ZO6RwzxrA5MhZXdFO64+7PT
S+GbebVO5vvuyctl33RdUpn9+cSdOiEtfRol8ellRINxjQMcxHiaRThmnXKRnmEcbDCa5x2R+OMJ
FV7FXK96NPavk7Pp1Sy1Ud0fn0GmzcP1TLkIF612AcyNR0crJ4SWMHe9CkQQs1QfwPdSiVJiLtH6
EhTt8nES3Eck5+U8A1zjgUoGGMGXNKQrA5MM+dYsRjrCyFLZA8exXYNtoLDN2EVGsh2W8ursbZCo
puK6aWsvp03DQp6ts0pK18xIjLh8nQW5tyD3F+TBgsy2eZ8WqYfLfyuRkjMD2sraLh6UQXCvaQjC
bIgR1tYEUSwF1n7TwHrok65Wt+z1xOsqjoER2VtX5Q4eQ5H5w+kXXxiYhZu6CwDzafUxvZN39B1J
vJNfAuDrQgAZcnP6hWpk0X7ZSgxl5rW0sobrqeKbZg3own2vkvgZ3Z62bPaA+LWVvXi1dr5tsHY+
XKMvgS40amUNl6DrKOyTq6H9ucHQFi6ur0YXW+Sg3eor+HhjdH9pMLoP18ZLKC5xjltZw/XMaqfd
NLv6cHl+JX5iNS3sFMc0zVDDh1sGpdTwpJU1XFMNi4ObZkBZfPJrNZyrDebOqJQX2imOhhoyGxVu
j9aJbnGU1BDdfXjMr05omxw/PbaAtNTCllhAWmMCe9NgeAvPGj2F7paHt8nxVfFxwRIavDKC3Wln
v3ImosmRVvEhxtIgn6zCuBzCTY62Co9Trgb4yWa4veL4qyHOQ9Ftk9XgqptiWjYue8Er2I9tB9Qw
te01Ol67f7toNbTwds+2vOww9WbQlg3WXq72Lr8NuBpp1fQY2N+8oBDxFI8UYAbVInMX7E1it+yt
WeYFrNneP+C9Gu2nm+fKRnIvVquLj0ctUM0V/T7Ew3mzlWr8LaJvGmuCC45olcGRt1kTxOaGaAVH
xMqAyNusCWJxCCa+aOSWhVyPIddfG7nmhlYFh+FKgWiubQj3mxtCFR13LoNi2mhNGJu7m1V88Lok
kLzZmlA2NzpacpWgDJYVZpb95m5cgU6SvrU2iLzNmiBuEuP87kE01GUr/MtB5G3WBLFs/PIiQTQN
tcJUzRutCeObxsKos8VOtpyMtCVQjoqhFMshVxypiC8VrmXXOJ8KrobFJEuuij4VWsVxyItFa8mF
1CdC66BhZ+aKr7w+FVi/n4s/Ypb2NdNmSBFdMyA7ytIKEPLEVRzT6pjs/FFabFiqOdCQ3IYwIKcl
HSOkKQSxy1/tFv+DV+WFkuI4pgyuHU+lvmJpjI++rTGIjmyXQDIginssZp/1+oph3f92WiiJuUhi
lhKdGIRLytOFpFUvvaW30Qy3dfQXqHYo6F3hy+xa0CMaXNAxDUUUjaOA34v8OA0fuSaZsyRmKcFZ
n+B7fcK/y2UdMFwzNj6YI3iGNMKSoYJV7kqkhKR1AR3ZlcSUgLylyNoPLA8EVzxxroa2qg4wy7uD
rsrWw3ma9oub94uL1AFUYSAw6CWRU5IKfSjvtdu/tNoHLbY1xgukAXuovm6/ftNm5xt5VhqkdTtv
W+3XUB2Ked0hwvxeYJttCPOMZKIhH1bsgBtLmVKwr0hiSkrYtBWNdV5KSLoxcgiTPyUk10Wsocs1
7O4n0xLoRANAbL/d22/zm0EGV94HtdMSyfimdpqTTAYlENoPgFGekQaqeoRUpqpi3pFino5afdMb
wSuhBzhNFP7A6fUNTcb7hFkhTkt29+9IJbI+6EFZlmGFHv9KqvbzrHRsY2wN+vKx4R639/babD0j
L5NcrIKVIyjrtkVWUgbkyMZpcUaz2hpyZMwrMgoM3ZDbJnZFQGP7HVlW6iErU1BQwoxSHWxzZgUA
ZZ6BQQ1fxKZi9Vif3cml90I1udPZTTufZcD+Hlt2jiOI6TJTSH5l77f7jm0hi3WuipGJFDc1xmbG
AMGK5ZqEjLIa0H+aZ1vfmJ47xRL/ise7WYBfi/9BlUVxVkXVe2Leh1m/iX786fCjP5nROMv4Y/9G
/s93/wM=</CLUSTD>
    </CWBCIDATAOBJ>
    <CWBCIDATAOBJ>
     <RELID>CI</RELID>
     <INSTA>0020751259</INSTA>
     <PAKID>6</PAKID>
     <ALEID>0000589747</ALEID>
     <VERSNO>0002</VERSNO>
     <PGMID>LIMU</PGMID>
     <OBJTYPE>FUNC</OBJTYPE>
     <OBJNAME>ISHMED_QUIT_SERVICE</OBJNAME>
     <OBJVERSNO>99990</OBJVERSNO>
     <CLUSTR>1163</CLUSTR>
     <CLUSTD>/wYCAQICgAA0MTAzAAAAAJIcAAASH50CVGd1O47aUJiLSu0D9K69sHIzUtUMmelmtxoxrBxwsu6C
ocaZn6qSRTZkBm2AKJCZ2T5i+1I1kP+EyaRMQvdcEMc+Pt9n+xzbHL79XhLyXfr4QdoiLUmTrsVT
l7jkSEyiUlfUMPGkEspqNckSv0iU0qch2qD0tyT92FTePwVD8OCNYz8KL2tnp40a8MJPUd8P7y5r
k2RQ/7X2XlXc+OnC7bmjNU3RN4wvRONl7T5JRhey/Pj4eBq7o9NPUSCnHYRGLe/+4A4nXqwqN3XT
4JqlI64jg0FV+YCgjqiqWIauKnbHxLpqYLOryHlZsVq/sVsbqe0u0RR59i+tJtBEKnY+mEjnv3cx
4w6iV1hDmVbWqFwh6hBLbTQaZ28UefpP0ZHDMIEMW0RWhXaKTND1IeEbjUL4DFmeTYPDIEMmIozb
kDFEiSPqtOsWnzeoCrM+IiIqqPpnKmHEvWCUfOG9YfTpcyynosgLJUVeN7DDoFi9wAuTmIdRwv27
MBp7/fJW+94wcYXJceAO/b9ew6I/4HOqr0bTHQ6jx22GFsW2Rc2Cpp8Oji38MPWcqvBNS+8aqAj9
4PAU2RZlVQ3eplaHwsrXvm5bllEVCc2AjvMi8EVRR21M8Ibb/k/YYdM2MkBYmuEgGvf8ft8LjzSD
KwqIUqR/pfQNC3691DVYFI1tihHRVyEP4PWwaEc0MEF1Bxlo88w4Jo2uuBrVNcs0ISm3ymVIzKeh
7mgUoaLlPPwZVsjQbh8cO3NlaOA/yu91L0ATnSmrW+3juaCItqPiMctO8WzYqe5ONB3zBocDQHVQ
4d2r3DBftH0Xo7egjivFx6stR4bXLEJewd/LsuhSx6JVMtAhg85a65EpZLeBcnFYkoENxSsKYqjS
lbDFHixsd8tdfcqSoJaNKLutkgNN7+WIaJW6BO1WujEwbO4YvjwvL6W9sixhSwTUxzxXOMuErder
SpqoW5jfkSLZmrJbJpdaQ9M3Qnq7ir1eryriik0s9eysoch5UfAmDN2IUcEWtNkNO282MzWkAqCL
HeoCDGPu8nDgDkGaTQRp6WewQ2qCdP3N2XnjbQaEBNFl+1uwchFYwvyQh0PPz+Ee0uKzeCWwkr2A
QCksYT7gYmwLtOB5tP+MxRO35z+tDC7+UvfDvvd0ugywJPtjTX2Dx+6DxxM/8OLEDUY5GkhjSASJ
aW/Dy7F+aTbfbcWS5x4pfFacDJvo8nqPmSImIkSKXVmwvZv4S0wysn58z6OQR4PB9snJ6L47f9t8
2dRskJuRkgtC8vlIPT/PZ2lXqOYSuH7Iw573CC5BkhVO9/EdZDgIt0Fy7/Eg6k9iYeWkdQKARcFq
JTzZyy4AmoEgXdDb3nv3ys/tCZbCpXt+OEoAQSAKCyy+wDOmBKFhgNleDE46Xcyxw+EVxAZsGehk
v+ECbKaZX0w6e/YTMvaSyTgUs5x5a1HArsmeTlo8jwASfRonlyD9KMaT8cTbZLEDcKfXy1vOrFx3
88CUt5yt8sanOXn5w508+wio/vPNvw==</CLUSTD>
    </CWBCIDATAOBJ>
    <CWBCIDATAOBJ>
     <RELID>CI</RELID>
     <INSTA>0020751259</INSTA>
     <PAKID>6</PAKID>
     <ALEID>0000589747</ALEID>
     <VERSNO>0002</VERSNO>
     <PGMID>LIMU</PGMID>
     <OBJTYPE>FUNC</OBJTYPE>
     <OBJNAME>ISHMED_QUIT_SERVICE</OBJNAME>
     <OBJVERSNO>99990</OBJVERSNO>
     <DELTA_MODE>N</DELTA_MODE>
     <CLUSTR>2684</CLUSTR>
     <CLUSTD>/wYCAQICgAA0MTAzAAAAAPtYAAASH50C7d76mhtFjrgfrir3AfIBiOsq3ktORrK9e3sOyxaCQSZG
wA4jRecXCtljm7KMXIDWu/tl8pKPcW/7luRDpWcAyWsjCyEHn1F5d3qGGej+TU9P9/z5wx+34Pc9
+++7rYKftqVsEfj3762t0X+l95+uJ8JHGsXBNHy33dltbws0PJ2eBeHFu+1Zct56u/1elvz406E/
9m/u1YS2YXwID99tXybJzaEo3t7e7sb+ze7p9FpkDaDGdtr8oz+Z0ViWRq2+6Y00hSiypHQVh6AR
EWVJMyzVhBRZpq7J0nDECQMDiV3dVHrwTB9YqqX0kWy4R32keR8GBvFchIeGiiRx/lRSMFJkq2Pa
kshJSVGJMUTyCPIpJfWQhbBCkMZeixECfpDchl+L/8Hb8kKpZ9pdhbFm2qrnYGPIuBwRZHVkTRIz
Ki3ZkztZyV5Wsp9XPsiJ10CId8QTM4kZ+4QJnhNzsV0HKy77VkqUhsFRMKQEYRl5CGMbS+KiSDo2
LE12JJGn0hBh17AtBgGIkOckl/WOrNPLCY2u6eRsFl7QEBjhxUyM/y/XumprqDLXs/AqAV2NQZup
0PrzRfK3+jjvQYZU5fzDLEiSgEY0PKOR0A8SPxrTIKFRXfzriml6oO7HSHsow6gc+v5kIgRxIoxB
jiCJhQsa39AoSuqSwcAesoYGtq0+sip3BQo/BtE0vKZhfYx7zEjZVlWWFa71wo6+A8Bf0DENBVHY
QTvROArY8K13KBieypSpr1Tugr4Pmh/4E392Hs3OBRoBNU4E2xJtXa9TDFzZFDnnE3pBJxTGA1jQ
Gnk2bRd5XfSPqox36S294EZf8Mfx6eUkoF//CZkU/No1ye73jcp6pE6vr4NE+KsQfw5PL2FQU2FI
o/Hs9BIEfCaJkGFho7JtCsIoOL2sV6WezpEQYjoZ8wni0oeJblKbX2F4PfDsBv2qUvS+/jZJgosr
Nq2d+cnsukbGnQ3cimFfEV5Zs0i4SAX4SbilYSgYnmV7ju0MHOGdsDPa+bE+cUxkuMTTqs8NZmZS
034Q/EksDKfgLE241ap7NKfiEKOyZs3F+QK6dUeaXeGVG9BLKtyBrM5uAk/QI0q38rBnviD3/uZT
R33M58pdlXnbOhSc6c3sRpiF4IicRV9/O72q34uycc/QKssQXRhnP4ELzibys4AKPK5QoOAGxDlP
hNsgOqtbIlcZIuaiVxXKnYJWnfmxcMdHZ1EGTIk0ApGgr2j4vmZ5NhglGvi5oRBcC3qXDRYuxnN5
Wi5RiKdYul05CAnPp4B/xIxZnIBxjgU/vPHj+NmcR6JgQ9/YMF/5iT+Z1j6zEIOYqLrXFcZguZIg
oZP6WD6xya+Vje7JDLQnZIAnn2+EVycwt5uU6Y4PisSMl0Wckz/VNgXa5AjhZa5vufUQcNaF1P3l
qyIQzF7QJKJJ3TMJRoq2mSSZFGMa5J3COiSPFOuSI509nkoOd25vn0WWX93NRHE/wwC/bmUSvfqy
252LxX2uMxoLzAmjcW1Dhk0fxwiDu1rVBvTo13+xBdCECkp4RaN8+aTuEUM8qwNTYWU3hTvu/uz0
UvhmXq2T+b578nLZN12XVGZ/PnGnTkhLn0ZJfHoZ0WBc4wAHMZ5mEY5Zp1ykZxgHG4zmeUck/nhC
hVcx16sejf3r5Gx6NUttVPfHZ5Bp83A9Uy7CRatdAHPj0dHKCaElzF2vAhHELNUH8L1UopSYS7S+
BEW7fJwE9xHJeTnPANd4oJIBRvAlDenKwCRDvjWLkY4wslT2wHFs12AbKGwzdpGRbIelvDp7GySq
qbhu2trLadOwkGfrrJLSNTMSIy5fZ0HuLcj9BXmwILNt3qdF6uHy30qk5MyAtrK2iwdlENxrGoIw
G2KEtTVBFEuBtd80sB76pKvVLXs98bqKY2BE9tZVuYPHUGT+cPrFFwZm4abuAsB8Wn1M7+QdfUcS
7+SXAPi6EECG3Jx+oRpZtF+2EkOZeS2trOF6qvimWQO6cN+rJH5Gt6ctmz0gfm1lL16tnT83WDsf
rtGXQBcatbKGS9B1FPbJ1dC+bTC0hYvrq9HFFjlot/oKPt4Y3V8ajO7DtfESikuc41bWcD2z2mk3
za4+XJ5fiZ9YTQs7xTFNM9Tw4ZZBKTU8aWUN11TD4uCmGVAWn/xaDedqg7kzKuWFdoqjoYbMRoXb
o3WiWxwlNUR3Hx7zqxPaJsdPjy0gLbWwJRaQ1pjA3jQY3sKzRk+hu+XhbXJ8VXxcsIQGr4xgd9rZ
r5yJaHKkVXyIsTTIJ6swLodwk6OtwuOUqwF+shlurzj+aojzUHTbZDW46qaYlo3LXvAK9mPbATVM
bXuNjtfu3y5aDS283bMtLztMvRm0ZYO1l6u9y28DrkZaNT0G9jcvKEQ8xSMFmEG1yNwFe5PYLXtr
lnkBa7b3D3ivRvvp5rmykdyL1eri41ELVHNFvw/xcN5spRp/i+ibxprggiNaZXDkbdYEsbkhWsER
sTIg8jZrglgcgokvGrllIddjyPXXRq65oVXBYbhSIJprG8L95oZQRcedy6CYNloTxubuZhUfvC4J
JG+2JpTNjY6WXCUog2WFmWW/uRtXoJOkb60NIm+zJoibxDi/exANddkK/3IQeZs1QSwbv7xIEE1D
rTBV80ZrwvimsTDqbLGTLScjbQmUo2IoxXLIFUcq4kuFa9k1zqeCq2ExyZKrok+FVnEc8mLRWnIh
9YnQOmjYmbniK69PBdbv5+KPmKV9zbQZUkTXDMiOsrQChDxxFce0OiY7f5QWG5ZqDjQktyEMyGlJ
xwhpCkHs8le7xf/gVXmhpDiOKYNrx1Opr1ga46NvawyiI9slkAyI4h6L2We9vmJY97+dFkpiLpKY
pUQnBuGS8nQhadVLb+ltNMNtHf0Fqh0Kelf4MrsW9IgGF3RMQxFF4yjg9yI/TsNHrknmLIlZSnDW
J/hen/DvclkHDNeMjQ/mCJ4hjbBkqGCVuxIpIWldQEd2JTElIG8psvYDywPBFU+cq6GtqgPM8u6g
q7L1cJ6m/eLm/eIidQBVGAgMeknklKRCH8p77fYvrfZBi22N8QJpwB6qr9v77Z+Z38Oz0iCt24G6
b1ts5YwXsKuB/F5gey+9GQi9aKIhH1bsgBtLmVKwr0hiSkrYtBWNdV5KSLoxcgiTPyUk10Wsocs1
7O4n0xLoRANAbL/tvGbnrNKcZDyonZZIxje105xkMiiB0H4AjPKMNFDVI6QyVRXzjhTzdNTqm94I
Xgk9wGmi8AdOr29oMt4nzApxWrK7f0cqkfVBD8qyDCv0+FdStZ9npWMbY2vQl48N97i9t9dm6xl5
meRiFawcQVm3LbKSMiBHNk6LM5rV1pAjY16RUWDohtw2sSsCGtvvyLJSD1mZgoISZpTqYJszKwAo
8wwMavgiNhWrx/rsTi69F6rJnc5uWxKzDNjfY8vOcQQxXWYKya/s/XbfsS1ksc5VMTKR4qbG2MwY
IFixXJOQUVYD+k/zbOsb03OnWOJf8Xg3C/Br8T+osijOqqh6T8z7MOs30Y8/HX70JzMaZxl/7N/I
//nufw==</CLUSTD>
    </CWBCIDATAOBJ>
   </CWBCIDATAOBJ>
   <CWBCIDATAOBJ_field_catalog>
    <item>
     <POS>1</POS>
     <NAME>RELID</NAME>
     <TYPE_KIND>C</TYPE_KIND>
     <LENGTH>2</LENGTH>
     <IS_KEY>X</IS_KEY>
    </item>
    <item>
     <POS>2</POS>
     <NAME>INSTA</NAME>
     <TYPE_KIND>C</TYPE_KIND>
     <LENGTH>10</LENGTH>
     <IS_KEY>X</IS_KEY>
    </item>
    <item>
     <POS>3</POS>
     <NAME>PAKID</NAME>
     <TYPE_KIND>C</TYPE_KIND>
     <LENGTH>10</LENGTH>
     <IS_KEY>X</IS_KEY>
    </item>
    <item>
     <POS>4</POS>
     <NAME>ALEID</NAME>
     <TYPE_KIND>N</TYPE_KIND>
     <LENGTH>10</LENGTH>
     <IS_KEY>X</IS_KEY>
    </item>
    <item>
     <POS>5</POS>
     <NAME>VERSNO</NAME>
     <TYPE_KIND>N</TYPE_KIND>
     <LENGTH>4</LENGTH>
     <IS_KEY>X</IS_KEY>
    </item>
    <item>
     <POS>6</POS>
     <NAME>PGMID</NAME>
     <TYPE_KIND>C</TYPE_KIND>
     <LENGTH>4</LENGTH>
     <IS_KEY>X</IS_KEY>
    </item>
    <item>
     <POS>7</POS>
     <NAME>OBJTYPE</NAME>
     <TYPE_KIND>C</TYPE_KIND>
     <LENGTH>4</LENGTH>
     <IS_KEY>X</IS_KEY>
    </item>
    <item>
     <POS>8</POS>
     <NAME>OBJNAME</NAME>
     <TYPE_KIND>C</TYPE_KIND>
     <LENGTH>120</LENGTH>
     <IS_KEY>X</IS_KEY>
    </item>
    <item>
     <POS>9</POS>
     <NAME>OBJVERSNO</NAME>
     <TYPE_KIND>N</TYPE_KIND>
     <LENGTH>5</LENGTH>
     <IS_KEY>X</IS_KEY>
    </item>
    <item>
     <POS>10</POS>
     <NAME>DELTA_MODE</NAME>
     <TYPE_KIND>C</TYPE_KIND>
     <LENGTH>2</LENGTH>
     <IS_KEY>X</IS_KEY>
    </item>
    <item>
     <POS>11</POS>
     <NAME>SRTF2</NAME>
     <TYPE_KIND>I</TYPE_KIND>
     <LENGTH>10</LENGTH>
     <IS_KEY>X</IS_KEY>
    </item>
    <item>
     <POS>12</POS>
     <NAME>CLUSTR</NAME>
     <TYPE_KIND>s</TYPE_KIND>
     <LENGTH>5</LENGTH>
    </item>
    <item>
     <POS>13</POS>
     <NAME>CLUSTD</NAME>
     <TYPE_KIND>X</TYPE_KIND>
     <LENGTH>2886</LENGTH>
    </item>
   </CWBCIDATAOBJ_field_catalog>
   <CWBCINSTATTR_field_catalog>
    <item>
     <POS>1</POS>
     <NAME>INSTA</NAME>
     <TYPE_KIND>C</TYPE_KIND>
     <LENGTH>10</LENGTH>
     <IS_KEY>X</IS_KEY>
    </item>
    <item>
     <POS>2</POS>
     <NAME>PAKID</NAME>
     <TYPE_KIND>C</TYPE_KIND>
     <LENGTH>10</LENGTH>
     <IS_KEY>X</IS_KEY>
    </item>
    <item>
     <POS>3</POS>
     <NAME>ALEID</NAME>
     <TYPE_KIND>N</TYPE_KIND>
     <LENGTH>10</LENGTH>
     <IS_KEY>X</IS_KEY>
    </item>
    <item>
     <POS>4</POS>
     <NAME>VERSNO</NAME>
     <TYPE_KIND>N</TYPE_KIND>
     <LENGTH>4</LENGTH>
     <IS_KEY>X</IS_KEY>
    </item>
    <item>
     <POS>5</POS>
     <NAME>ID</NAME>
     <TYPE_KIND>N</TYPE_KIND>
     <LENGTH>2</LENGTH>
     <IS_KEY>X</IS_KEY>
    </item>
    <item>
     <POS>6</POS>
     <NAME>VALUE</NAME>
     <TYPE_KIND>C</TYPE_KIND>
     <LENGTH>100</LENGTH>
    </item>
   </CWBCINSTATTR_field_catalog>
  </asx:values>
 </asx:abap>
</abapGit>
