<?xml version="1.0" encoding="utf-8"?>
<abapGit version="v1.0.0" serializer="ZCL_ABAPGIT_OBJECT_BY_SOBJ" serializer_version="1.0">
 <asx:abap xmlns:asx="http://www.sap.com/abapxml" version="1.0">
  <asx:values>
   <CWBCIHEAD>
    <CWBCIHEAD>
     <INSTA>0020751259</INSTA>
     <PAKID>6</PAKID>
     <ALEID>0000646031</ALEID>
     <VERSNO>0001</VERSNO>
     <FORMAT_ID>3</FORMAT_ID>
    </CWBCIHEAD>
   </CWBCIHEAD>
   <CWBCIHEAD_field_catalog>
    <item>
     <POS>1</POS>
     <NAME>INSTA</NAME>
     <TYPE_KIND>C</TYPE_KIND>
     <LENGTH>10</LENGTH>
     <IS_KEY>X</IS_KEY>
    </item>
    <item>
     <POS>2</POS>
     <NAME>PAKID</NAME>
     <TYPE_KIND>C</TYPE_KIND>
     <LENGTH>10</LENGTH>
     <IS_KEY>X</IS_KEY>
    </item>
    <item>
     <POS>3</POS>
     <NAME>ALEID</NAME>
     <TYPE_KIND>N</TYPE_KIND>
     <LENGTH>10</LENGTH>
     <IS_KEY>X</IS_KEY>
    </item>
    <item>
     <POS>4</POS>
     <NAME>VERSNO</NAME>
     <TYPE_KIND>N</TYPE_KIND>
     <LENGTH>4</LENGTH>
     <IS_KEY>X</IS_KEY>
    </item>
    <item>
     <POS>5</POS>
     <NAME>FORMAT_ID</NAME>
     <TYPE_KIND>I</TYPE_KIND>
     <LENGTH>10</LENGTH>
    </item>
    <item>
     <POS>6</POS>
     <NAME>INCOMPLETE</NAME>
     <TYPE_KIND>C</TYPE_KIND>
     <LENGTH>1</LENGTH>
    </item>
    <item>
     <POS>7</POS>
     <NAME>MANUAL_ACTIVITY</NAME>
     <TYPE_KIND>C</TYPE_KIND>
     <LENGTH>1</LENGTH>
    </item>
    <item>
     <POS>8</POS>
     <NAME>IS_TRANSPORTABLE</NAME>
     <TYPE_KIND>C</TYPE_KIND>
     <LENGTH>1</LENGTH>
    </item>
   </CWBCIHEAD_field_catalog>
   <CWBCIDATA_field_catalog>
    <item>
     <POS>1</POS>
     <NAME>RELID</NAME>
     <TYPE_KIND>C</TYPE_KIND>
     <LENGTH>2</LENGTH>
     <IS_KEY>X</IS_KEY>
    </item>
    <item>
     <POS>2</POS>
     <NAME>INSTA</NAME>
     <TYPE_KIND>C</TYPE_KIND>
     <LENGTH>10</LENGTH>
     <IS_KEY>X</IS_KEY>
    </item>
    <item>
     <POS>3</POS>
     <NAME>PAKID</NAME>
     <TYPE_KIND>C</TYPE_KIND>
     <LENGTH>10</LENGTH>
     <IS_KEY>X</IS_KEY>
    </item>
    <item>
     <POS>4</POS>
     <NAME>ALEID</NAME>
     <TYPE_KIND>N</TYPE_KIND>
     <LENGTH>10</LENGTH>
     <IS_KEY>X</IS_KEY>
    </item>
    <item>
     <POS>5</POS>
     <NAME>VERSNO</NAME>
     <TYPE_KIND>N</TYPE_KIND>
     <LENGTH>4</LENGTH>
     <IS_KEY>X</IS_KEY>
    </item>
    <item>
     <POS>6</POS>
     <NAME>SRTF2</NAME>
     <TYPE_KIND>I</TYPE_KIND>
     <LENGTH>10</LENGTH>
     <IS_KEY>X</IS_KEY>
    </item>
    <item>
     <POS>7</POS>
     <NAME>CLUSTR</NAME>
     <TYPE_KIND>s</TYPE_KIND>
     <LENGTH>5</LENGTH>
    </item>
    <item>
     <POS>8</POS>
     <NAME>CLUSTD</NAME>
     <TYPE_KIND>X</TYPE_KIND>
     <LENGTH>2886</LENGTH>
    </item>
   </CWBCIDATA_field_catalog>
   <CWBCIDPNDC_field_catalog>
    <item>
     <POS>1</POS>
     <NAME>INSTA</NAME>
     <TYPE_KIND>C</TYPE_KIND>
     <LENGTH>10</LENGTH>
     <IS_KEY>X</IS_KEY>
    </item>
    <item>
     <POS>2</POS>
     <NAME>PAKID</NAME>
     <TYPE_KIND>C</TYPE_KIND>
     <LENGTH>10</LENGTH>
     <IS_KEY>X</IS_KEY>
    </item>
    <item>
     <POS>3</POS>
     <NAME>ALEID</NAME>
     <TYPE_KIND>N</TYPE_KIND>
     <LENGTH>10</LENGTH>
     <IS_KEY>X</IS_KEY>
    </item>
    <item>
     <POS>4</POS>
     <NAME>VERSNO</NAME>
     <TYPE_KIND>N</TYPE_KIND>
     <LENGTH>4</LENGTH>
     <IS_KEY>X</IS_KEY>
    </item>
    <item>
     <POS>5</POS>
     <NAME>DEPTYPE</NAME>
     <TYPE_KIND>C</TYPE_KIND>
     <LENGTH>1</LENGTH>
     <IS_KEY>X</IS_KEY>
    </item>
    <item>
     <POS>6</POS>
     <NAME>CIINSTA_D</NAME>
     <TYPE_KIND>C</TYPE_KIND>
     <LENGTH>10</LENGTH>
     <IS_KEY>X</IS_KEY>
    </item>
    <item>
     <POS>7</POS>
     <NAME>CIPAKID_D</NAME>
     <TYPE_KIND>C</TYPE_KIND>
     <LENGTH>10</LENGTH>
     <IS_KEY>X</IS_KEY>
    </item>
    <item>
     <POS>8</POS>
     <NAME>CIALEID_D</NAME>
     <TYPE_KIND>N</TYPE_KIND>
     <LENGTH>10</LENGTH>
     <IS_KEY>X</IS_KEY>
    </item>
    <item>
     <POS>9</POS>
     <NAME>NTNUMM_D</NAME>
     <TYPE_KIND>N</TYPE_KIND>
     <LENGTH>10</LENGTH>
     <IS_KEY>X</IS_KEY>
    </item>
   </CWBCIDPNDC_field_catalog>
   <CWBCIFIXED_field_catalog>
    <item>
     <POS>1</POS>
     <NAME>INSTA</NAME>
     <TYPE_KIND>C</TYPE_KIND>
     <LENGTH>10</LENGTH>
     <IS_KEY>X</IS_KEY>
    </item>
    <item>
     <POS>2</POS>
     <NAME>PAKID</NAME>
     <TYPE_KIND>C</TYPE_KIND>
     <LENGTH>10</LENGTH>
     <IS_KEY>X</IS_KEY>
    </item>
    <item>
     <POS>3</POS>
     <NAME>ALEID</NAME>
     <TYPE_KIND>N</TYPE_KIND>
     <LENGTH>10</LENGTH>
     <IS_KEY>X</IS_KEY>
    </item>
    <item>
     <POS>4</POS>
     <NAME>VERSNO</NAME>
     <TYPE_KIND>N</TYPE_KIND>
     <LENGTH>4</LENGTH>
     <IS_KEY>X</IS_KEY>
    </item>
    <item>
     <POS>5</POS>
     <NAME>DEPAKID_F</NAME>
     <TYPE_KIND>C</TYPE_KIND>
     <LENGTH>10</LENGTH>
     <IS_KEY>X</IS_KEY>
    </item>
    <item>
     <POS>6</POS>
     <NAME>DEALEID_F</NAME>
     <TYPE_KIND>N</TYPE_KIND>
     <LENGTH>10</LENGTH>
     <IS_KEY>X</IS_KEY>
    </item>
   </CWBCIFIXED_field_catalog>
   <CWBCIVALID>
    <CWBCIVALID>
     <INSTA>0020751259</INSTA>
     <PAKID>6</PAKID>
     <ALEID>0000646031</ALEID>
     <VERSNO>0001</VERSNO>
     <TRPAKID>6</TRPAKID>
     <TRTYPEID>P</TRTYPEID>
     <TRALSID>000051</TRALSID>
     <DEPAKID_LO>6</DEPAKID_LO>
     <DEALEID_LO>0000000395</DEALEID_LO>
     <DEPAKID_HI>6</DEPAKID_HI>
     <DEALEID_HI>0000000731</DEALEID_HI>
    </CWBCIVALID>
   </CWBCIVALID>
   <CWBCIVALID_field_catalog>
    <item>
     <POS>1</POS>
     <NAME>INSTA</NAME>
     <TYPE_KIND>C</TYPE_KIND>
     <LENGTH>10</LENGTH>
     <IS_KEY>X</IS_KEY>
    </item>
    <item>
     <POS>2</POS>
     <NAME>PAKID</NAME>
     <TYPE_KIND>C</TYPE_KIND>
     <LENGTH>10</LENGTH>
     <IS_KEY>X</IS_KEY>
    </item>
    <item>
     <POS>3</POS>
     <NAME>ALEID</NAME>
     <TYPE_KIND>N</TYPE_KIND>
     <LENGTH>10</LENGTH>
     <IS_KEY>X</IS_KEY>
    </item>
    <item>
     <POS>4</POS>
     <NAME>VERSNO</NAME>
     <TYPE_KIND>N</TYPE_KIND>
     <LENGTH>4</LENGTH>
     <IS_KEY>X</IS_KEY>
    </item>
    <item>
     <POS>5</POS>
     <NAME>TRPAKID</NAME>
     <TYPE_KIND>C</TYPE_KIND>
     <LENGTH>10</LENGTH>
     <IS_KEY>X</IS_KEY>
    </item>
    <item>
     <POS>6</POS>
     <NAME>TRTYPEID</NAME>
     <TYPE_KIND>C</TYPE_KIND>
     <LENGTH>1</LENGTH>
     <IS_KEY>X</IS_KEY>
    </item>
    <item>
     <POS>7</POS>
     <NAME>TRALSID</NAME>
     <TYPE_KIND>N</TYPE_KIND>
     <LENGTH>6</LENGTH>
     <IS_KEY>X</IS_KEY>
    </item>
    <item>
     <POS>8</POS>
     <NAME>DEPAKID_LO</NAME>
     <TYPE_KIND>C</TYPE_KIND>
     <LENGTH>10</LENGTH>
     <IS_KEY>X</IS_KEY>
    </item>
    <item>
     <POS>9</POS>
     <NAME>DEALEID_LO</NAME>
     <TYPE_KIND>N</TYPE_KIND>
     <LENGTH>10</LENGTH>
     <IS_KEY>X</IS_KEY>
    </item>
    <item>
     <POS>10</POS>
     <NAME>DEPAKID_HI</NAME>
     <TYPE_KIND>C</TYPE_KIND>
     <LENGTH>10</LENGTH>
     <IS_KEY>X</IS_KEY>
    </item>
    <item>
     <POS>11</POS>
     <NAME>DEALEID_HI</NAME>
     <TYPE_KIND>N</TYPE_KIND>
     <LENGTH>10</LENGTH>
     <IS_KEY>X</IS_KEY>
    </item>
   </CWBCIVALID_field_catalog>
   <CWBCIOBJ>
    <CWBCIOBJ>
     <INSTA>0020751259</INSTA>
     <PAKID>6</PAKID>
     <ALEID>0000646031</ALEID>
     <VERSNO>0001</VERSNO>
     <PGMID>LIMU</PGMID>
     <OBJECT>FUNC</OBJECT>
     <OBJ_NAME>ISHMED_LSSTA</OBJ_NAME>
     <TRPGMID>R3TR</TRPGMID>
     <TROBJECT>FUGR</TROBJECT>
     <TROBJ_NAME>N1LD</TROBJ_NAME>
    </CWBCIOBJ>
   </CWBCIOBJ>
   <CWBCIOBJ_field_catalog>
    <item>
     <POS>1</POS>
     <NAME>INSTA</NAME>
     <TYPE_KIND>C</TYPE_KIND>
     <LENGTH>10</LENGTH>
     <IS_KEY>X</IS_KEY>
    </item>
    <item>
     <POS>2</POS>
     <NAME>PAKID</NAME>
     <TYPE_KIND>C</TYPE_KIND>
     <LENGTH>10</LENGTH>
     <IS_KEY>X</IS_KEY>
    </item>
    <item>
     <POS>3</POS>
     <NAME>ALEID</NAME>
     <TYPE_KIND>N</TYPE_KIND>
     <LENGTH>10</LENGTH>
     <IS_KEY>X</IS_KEY>
    </item>
    <item>
     <POS>4</POS>
     <NAME>VERSNO</NAME>
     <TYPE_KIND>N</TYPE_KIND>
     <LENGTH>4</LENGTH>
     <IS_KEY>X</IS_KEY>
    </item>
    <item>
     <POS>5</POS>
     <NAME>PGMID</NAME>
     <TYPE_KIND>C</TYPE_KIND>
     <LENGTH>4</LENGTH>
     <IS_KEY>X</IS_KEY>
    </item>
    <item>
     <POS>6</POS>
     <NAME>OBJECT</NAME>
     <TYPE_KIND>C</TYPE_KIND>
     <LENGTH>4</LENGTH>
     <IS_KEY>X</IS_KEY>
    </item>
    <item>
     <POS>7</POS>
     <NAME>OBJ_NAME</NAME>
     <TYPE_KIND>C</TYPE_KIND>
     <LENGTH>120</LENGTH>
     <IS_KEY>X</IS_KEY>
    </item>
    <item>
     <POS>8</POS>
     <NAME>TRPGMID</NAME>
     <TYPE_KIND>C</TYPE_KIND>
     <LENGTH>4</LENGTH>
    </item>
    <item>
     <POS>9</POS>
     <NAME>TROBJECT</NAME>
     <TYPE_KIND>C</TYPE_KIND>
     <LENGTH>4</LENGTH>
    </item>
    <item>
     <POS>10</POS>
     <NAME>TROBJ_NAME</NAME>
     <TYPE_KIND>C</TYPE_KIND>
     <LENGTH>40</LENGTH>
    </item>
   </CWBCIOBJ_field_catalog>
   <CWBCICATTR_field_catalog>
    <item>
     <POS>1</POS>
     <NAME>INSTA</NAME>
     <TYPE_KIND>C</TYPE_KIND>
     <LENGTH>10</LENGTH>
     <IS_KEY>X</IS_KEY>
    </item>
    <item>
     <POS>2</POS>
     <NAME>PAKID</NAME>
     <TYPE_KIND>C</TYPE_KIND>
     <LENGTH>10</LENGTH>
     <IS_KEY>X</IS_KEY>
    </item>
    <item>
     <POS>3</POS>
     <NAME>ALEID</NAME>
     <TYPE_KIND>N</TYPE_KIND>
     <LENGTH>10</LENGTH>
     <IS_KEY>X</IS_KEY>
    </item>
    <item>
     <POS>4</POS>
     <NAME>VERSNO</NAME>
     <TYPE_KIND>N</TYPE_KIND>
     <LENGTH>4</LENGTH>
     <IS_KEY>X</IS_KEY>
    </item>
    <item>
     <POS>5</POS>
     <NAME>CONFIRMED</NAME>
     <TYPE_KIND>C</TYPE_KIND>
     <LENGTH>1</LENGTH>
    </item>
    <item>
     <POS>6</POS>
     <NAME>CISTATUS</NAME>
     <TYPE_KIND>C</TYPE_KIND>
     <LENGTH>1</LENGTH>
    </item>
    <item>
     <POS>7</POS>
     <NAME>CONFIRM_ACTIVITY</NAME>
     <TYPE_KIND>C</TYPE_KIND>
     <LENGTH>1</LENGTH>
    </item>
   </CWBCICATTR_field_catalog>
   <CWBCIINVLD_field_catalog>
    <item>
     <POS>1</POS>
     <NAME>INSTA</NAME>
     <TYPE_KIND>C</TYPE_KIND>
     <LENGTH>10</LENGTH>
     <IS_KEY>X</IS_KEY>
    </item>
    <item>
     <POS>2</POS>
     <NAME>PAKID</NAME>
     <TYPE_KIND>C</TYPE_KIND>
     <LENGTH>10</LENGTH>
     <IS_KEY>X</IS_KEY>
    </item>
    <item>
     <POS>3</POS>
     <NAME>ALEID</NAME>
     <TYPE_KIND>N</TYPE_KIND>
     <LENGTH>10</LENGTH>
     <IS_KEY>X</IS_KEY>
    </item>
    <item>
     <POS>4</POS>
     <NAME>VERSNO</NAME>
     <TYPE_KIND>N</TYPE_KIND>
     <LENGTH>4</LENGTH>
     <IS_KEY>X</IS_KEY>
    </item>
    <item>
     <POS>5</POS>
     <NAME>TRPAKID</NAME>
     <TYPE_KIND>C</TYPE_KIND>
     <LENGTH>10</LENGTH>
     <IS_KEY>X</IS_KEY>
    </item>
    <item>
     <POS>6</POS>
     <NAME>TRTYPEID</NAME>
     <TYPE_KIND>C</TYPE_KIND>
     <LENGTH>1</LENGTH>
     <IS_KEY>X</IS_KEY>
    </item>
    <item>
     <POS>7</POS>
     <NAME>TRALSID</NAME>
     <TYPE_KIND>N</TYPE_KIND>
     <LENGTH>6</LENGTH>
     <IS_KEY>X</IS_KEY>
    </item>
    <item>
     <POS>8</POS>
     <NAME>DEPAKID_LO</NAME>
     <TYPE_KIND>C</TYPE_KIND>
     <LENGTH>10</LENGTH>
     <IS_KEY>X</IS_KEY>
    </item>
    <item>
     <POS>9</POS>
     <NAME>DEALEID_LO</NAME>
     <TYPE_KIND>N</TYPE_KIND>
     <LENGTH>10</LENGTH>
     <IS_KEY>X</IS_KEY>
    </item>
    <item>
     <POS>10</POS>
     <NAME>DEPAKID_HI</NAME>
     <TYPE_KIND>C</TYPE_KIND>
     <LENGTH>10</LENGTH>
     <IS_KEY>X</IS_KEY>
    </item>
    <item>
     <POS>11</POS>
     <NAME>DEALEID_HI</NAME>
     <TYPE_KIND>N</TYPE_KIND>
     <LENGTH>10</LENGTH>
     <IS_KEY>X</IS_KEY>
    </item>
   </CWBCIINVLD_field_catalog>
   <CWBCIDATAOBJ>
    <CWBCIDATAOBJ>
     <RELID>CI</RELID>
     <INSTA>0020751259</INSTA>
     <PAKID>6</PAKID>
     <ALEID>0000646031</ALEID>
     <VERSNO>0001</VERSNO>
     <PGMID>LIMU</PGMID>
     <OBJTYPE>FUNC</OBJTYPE>
     <OBJNAME>ISHMED_LSSTA</OBJNAME>
     <OBJVERSNO>99989</OBJVERSNO>
     <DELTA_MODE>O</DELTA_MODE>
     <CLUSTR>1190</CLUSTR>
     <CLUSTD>/wYCAQICgAA0MTAzAAAAANsOAAASH50C2n217TZuA1E/LNA+9akfIBj7VMChLwmaBgwXjEQ7qmlJ
JSlDeTLcRMkazSqBL5t8VL+k/anOkJRlJEY32V6xhpM5MxyZwzNDcvTVty34fI3/3rT2fKIWbxn4
+63V+uZX+u7xw23wsVyuFnfVabt30G0HZXV5d7Wobk7bm/V157j9jtH56vFk/vP8/oknPFutTmDw
tP1+vb4/IeTh4eFgNb8/uLz7QPAB8Gi7xz/ObzflitGiM5GzIuKGM8rPeGZEYQijUZyEEqRI5DBi
dFpYECuASg8lH8HYME/ChE8Ei/X5REQzqbXhlGzNlCvBWdKTESUWUh6aeCpYAbpDdCQSobgREf6e
EgICEawLn479wq/VRjqS6RnHmGQazjIVTzG8woikx2ACj5ylXw8NanBYgyMAZGc5xK8Qoza40Bps
l6kzxTVO4cCnl51xBdIIxUQ92JjoOE4illFiJZ0KpeM0wSX3IC6vUY1pYOXjulxW5TKQ5WK13lQ3
q9V6vt6sIBQ7jgv5R+KOZyJOVPy5cc9/WW/K29syEItqubh8j6H/CzHbQfG5QS+q/4jsJDWzYZon
0fPIi9dEHkTz5WoNvEPsQYW0B4sqgO2HUwc35fWmuiqrPcshXg5zmN+tzoGX7/Q/L3kLzUUmWJ0d
q0D4Kg9NrgTzUXb8s80AjcSQ59JM7c5XYiiUSEIBOMtSHRukARhpFJpmKK07zgIilFxr9/SsxjJO
xCwdohM/kx4qYRfca2C/gYMGHjbQHyd/C3X7dl3DVm1/Rl2qRh3/4Ot4638xvO3Z+S8gbrfmxGvJ
G3wh5O0/fRrCiv3skReRdPi/IYl4OYlkigwZd/sX5tVNTWaF5pl0nY3TKfZLeSRYD3ZVjT/V0fAs
kyyBZgglnfDEdkGTNEJuzlONjVhuuB4TP+1swuPk6dzOSEm9FuKlGZrY2CVa+RfuKndjxLpz/t2k
vDoJxncVNJ7rRbnEq+aqXAW+U6mC+eYaDFXg76SquU2fXKZ1WMRLo3xC1JOE2BDsenPk1kf0kyxg
TEQGxZQr26xG0L9KpilxAPSEs+gt6gBstZFt7aVhmCvUdX4W4iFhpcuJrnOiRZiDC/KAtFNiEQ0h
f6zf7R51uv1OH6rcGmi+dbOI5s6tB3k/7PR/ALN1g+vb3uT1XQ7Jk2JqdxEQj0lXWAvoQomDVMmU
2+qIi8zgpnSAai3wAW0LancqZ4HUxcBX77g3GBwj+bGt1WfezkLjxhsW5TQqkT0A0VugpVZoHobn
IsTKJHXOSC133yksNtwOZKNJHDE1MApK12Kanv0ooPcY5iOweQWNMzuLq/KtSsepUkk+YeNYj7v9
3tH3QFBto1qF+gLKy6egUSnPzXmqnNlj9I5ExpR1RATn2dSeQXijwqxbFd9RfC1CvXkUZiq1wQZA
ylaBPQwzKsmTEe6vHc11cBE7Puj6/i3CU3acpDWNsEqNJ565wJ9PJ1maiARzGyohBdfuyJV+fqN4
oqUxhffAV6iZaxC3B82OmdpZZjbLAXw69gsujdm7hMMRqVPo00Z23xdJ/e7Jfn/zBw==</CLUSTD>
    </CWBCIDATAOBJ>
    <CWBCIDATAOBJ>
     <RELID>CI</RELID>
     <INSTA>0020751259</INSTA>
     <PAKID>6</PAKID>
     <ALEID>0000646031</ALEID>
     <VERSNO>0001</VERSNO>
     <PGMID>LIMU</PGMID>
     <OBJTYPE>FUNC</OBJTYPE>
     <OBJNAME>ISHMED_LSSTA</OBJNAME>
     <OBJVERSNO>99990</OBJVERSNO>
     <CLUSTR>1140</CLUSTR>
     <CLUSTD>/wYCAQICgAA0MTAzAAAAAOIcAAASH50CVp217DZuQ1EtCrQf0F27ILyYRQCFzrRBi4yiASVdJ2wk
UqDoJi4KCHaspMbYcmApk8ns+3PtT5WSn3GssR3FVocL+ZqPcw7Jy0uK+vZ7TaXvsscP2opkabZ2
qZ6OFmqBJjWhNVWOVE+hQZ5ra1z9grKyp6vKiPaPpv34t/H+06CPPkajpDeMT2tHh/UaiuLrYbcX
357W7tMb/dfae9NoJ59O2p323VJN1TZOTlThae2vNL07wfjh4eEwad8dXg8HOGugatTGzT+2+/dR
YhpXuueGNncgdMCVxDTOgTggTIO7jmn4Zx51TJd6TQOPbYNbv8mWD2ajyWwDT/9l2Yx4YNLg3AMn
dINAkrw4zzV+BxEwbtZVOjLw5J/hQCApI5Jyhk1VO6NkcLkb3nohb06Jpx1XABI8YDL0iZQgWKDy
7EsrnBWYhuQXwFSGMP/MUjwMo8Fd+hh2+sPrDwnOkoHnlQy8DLAGUM3XIIrTJIyHadi7jYejqFse
tRv107aCHA3a/d7n10Ds3YQzqa8ms93vDx9WAc3NBhdeQdHBzrmVA2aeUxW/x52mC0XsO6cX4HMh
q+q8L/iZIJXPve5z7lYlwnZJEGxEPjcdaFBGn7nt/0Qd9Xw3JySlFd4MR51etxvFexrBJxVACHC+
UvkuJ1+vdJsUrcaGoMCcp5Q78HpSFBFdykAPwIXne8Y+ZTQDELrNPY+wcrNcRsRsGPTAFgBF07n7
PaxQod/YOXfuysSlf5SPdRuwqcZC6ryxPxdUq22vfJL7GZ9Pzqo7E036/EzDDqjOoPDsVa6bG4Xv
YnaLOLRSfvq0ZM/0NmfsFfy9rIqmCLioUoFDJAmWSvcsIT8NlFuHJRX4RL2igIRKZ8JXMVhhN8sd
fcqKENwHIVtVahDZuRyYXalLiGalgUFSb0338cxeuPbK7wUttaAuxreD05uw5XzTyG7o5vBrrkie
3tUtqspgYPIqKFpPSZfzTUOdrRk339YNPLaUXibhSvWGWMSXV/Lt8XFeC0yE2FHOdwEtHSgTFKFT
RMPcPMwBQPEvtvsyRm5AjjE2NwYRQBwkieUCaljhBBJdUnmOFPACB7IoU71FARBhn6/Gx7MuqzFR
IWclI22goKUHTUvY6E0/fffmNn2H6gWAUxzK1CvD6qFUeDedMD7qJ0na1qNePOqpgeiFuXWIamej
dvq5j9Qc67/8VP+5vunI5MjJo57cd0bX65VOFeIC9/iy1xxv5DXgBpvPrEow9gY1HPO5HfvKxijq
MEkbL55t1Xq6+jZjxFs7wAHqRLe9GL10mrcc0/GbBDpADcE9NPE6RJnkk1U098UtJgpdnqtdAS07
7xayuJAL1MhqodyItsBYCAULSLNQMMn4ED1uEgpWMmyzoAoGShAaAMo+RNwM7+PuFm23XTwoCscj
cLoYX/LnNqzF62dF/W1qH6Ao7r7Q7deuy7XhDK/YGMd1n2/HeMXOjZ996sOLHwLx9KOi+e83/wE=</CLUSTD>
    </CWBCIDATAOBJ>
    <CWBCIDATAOBJ>
     <RELID>CI</RELID>
     <INSTA>0020751259</INSTA>
     <PAKID>6</PAKID>
     <ALEID>0000646031</ALEID>
     <VERSNO>0001</VERSNO>
     <PGMID>LIMU</PGMID>
     <OBJTYPE>FUNC</OBJTYPE>
     <OBJNAME>ISHMED_LSSTA</OBJNAME>
     <OBJVERSNO>99990</OBJVERSNO>
     <DELTA_MODE>N</DELTA_MODE>
     <CLUSTR>1201</CLUSTR>
     <CLUSTD>/wYCAQICgAA0MTAzAAAAAOgOAAASH50C6b5qdhu3gbAPC7SnnvoAgrGnAg5tJ0bTgOGCkWhHNS2p
JGUoJ8NNlF2jWSXwzyavtq/QvlRnSMpyE6ObbH+xgpP5ZjgU54/k6KtvW/B8jf9etfY8UYu3DPz9
2mp985G+eXh/E3wol6vFbXXa7h1020FZXd5eLaq3p+3N+rpz3H7D6Hz1cDL/eX73SBPmVqsTGDxt
v1uv704Iub+/P1jN7w4ub98TnAAabTf9w/xmU64YLToTOSsibjij/IxnRhSGMBrFSSiBikQOI0an
hQWxAqj0UPIRjA3zJEz4RLBYn09ENJNaG07JVky5EpwlPRlRYiHloYmnghXAO0RHIhGKGxHh+5QQ
YIhgXXg69gdvq4V0JNMzjjbJNJxlKp6ieYURSY/BAh45Sb8eOqzBUQ0GAMiOO8R7iFYbdLQGWzd1
prjGJRz4tNsZV0CNUEzUg42IjuMkYhklltKpUDpOE3S5B3Z5jmpMAysf1uWyKpeBLBer9aZ6u1qt
5+vNCkyx4+jIP2J3PBNxouLPtXv+y3pT3tyUgVhUy8XlOzT9X7DZDorPNXpR/UfBTlIzG6Z5Ej21
vHiJ5UE0X67WEHewPagw7MGiCmD74dLB2/J6U12V1R53iKfDHNZ33jnw/J3+5yVvobnIBKuzYxkw
X+WhyZVg3sqOn9sM0EgMeS7N1O58JYZCiSQUgLMs1bHBMEBEGoamGVKrjqsACSXX2s2e1VjGiZil
Q1TiZ9JDJazDvQb2G3jYwKMG+uPkbwndvl3XRKuWPwldqkYdP/Flcet/MXHbs/OfEbjdmhMvDd7h
FxK8/adPE7Bif/TIs4J09L8JEvF0EskUI2Tc7V+YFzc1mSWaZ9J1No6n2C/lkWA92FU1/lRHw7NM
sgSaIaR0whPbBU3SCGNznmpsxHLD9Zj4ZWcTHieP13ZCSmpfiKdmaGJjXbT0L9xV7saIdef8u0l5
dRKMbytoPNeLcolXzVW5CnynUgXzzTUIqsDfSVVzmz66TGuziKdG+YSoRwmxJlh/c4ytt+gnWcCY
iAySKVehxEp1gEbQx0qmKXEA+ISz6DXyAGzVkW0NpmGYK+R1fhbiYWGpy42uc6NFmIMKxgPDT4lF
NIQ8sn63O+h0+50+VLsV0BwHw0F3cHw4gHPCsjR3ur0fOr1+pwu6VoA3u73Wu92+vdghk1JM7ZaC
LGAFKCwMVKHEQapkym2pxEVm0G8HqNYCJ2hbXbtLOQnkMYbg9XqD7wc9zERsC/eJtpPQ+A/ajqMS
Qwggeg2xqRmah+G5CLFMSZ1AUtPdDwyLDbcD2WgSR0wdGgV1bDFNz34U0IgM8xHIPIPCmV3FlfyW
peNUqSSfsHGsx90+mAkBqmVUq1BfQK35dDUs5bk5T5UTe4zakciYsoqI4HCb2gMJr1dYdcviB4sv
TCg+j8JMpdbYAIKyZWBDw4pK8mSEm22Hc+1cxI4Pur6Zi/DIHSdpHUbwUuPxZy7w9ekkSxORYG5D
JaTg2p2/0q9vFE+0NKbwGvg9NXPd4vbU2RFTu8rMZjmAp2N/oNKIvUo4HJE6hT5tZPfjkdQfouy3
V78D</CLUSTD>
    </CWBCIDATAOBJ>
   </CWBCIDATAOBJ>
   <CWBCIDATAOBJ_field_catalog>
    <item>
     <POS>1</POS>
     <NAME>RELID</NAME>
     <TYPE_KIND>C</TYPE_KIND>
     <LENGTH>2</LENGTH>
     <IS_KEY>X</IS_KEY>
    </item>
    <item>
     <POS>2</POS>
     <NAME>INSTA</NAME>
     <TYPE_KIND>C</TYPE_KIND>
     <LENGTH>10</LENGTH>
     <IS_KEY>X</IS_KEY>
    </item>
    <item>
     <POS>3</POS>
     <NAME>PAKID</NAME>
     <TYPE_KIND>C</TYPE_KIND>
     <LENGTH>10</LENGTH>
     <IS_KEY>X</IS_KEY>
    </item>
    <item>
     <POS>4</POS>
     <NAME>ALEID</NAME>
     <TYPE_KIND>N</TYPE_KIND>
     <LENGTH>10</LENGTH>
     <IS_KEY>X</IS_KEY>
    </item>
    <item>
     <POS>5</POS>
     <NAME>VERSNO</NAME>
     <TYPE_KIND>N</TYPE_KIND>
     <LENGTH>4</LENGTH>
     <IS_KEY>X</IS_KEY>
    </item>
    <item>
     <POS>6</POS>
     <NAME>PGMID</NAME>
     <TYPE_KIND>C</TYPE_KIND>
     <LENGTH>4</LENGTH>
     <IS_KEY>X</IS_KEY>
    </item>
    <item>
     <POS>7</POS>
     <NAME>OBJTYPE</NAME>
     <TYPE_KIND>C</TYPE_KIND>
     <LENGTH>4</LENGTH>
     <IS_KEY>X</IS_KEY>
    </item>
    <item>
     <POS>8</POS>
     <NAME>OBJNAME</NAME>
     <TYPE_KIND>C</TYPE_KIND>
     <LENGTH>120</LENGTH>
     <IS_KEY>X</IS_KEY>
    </item>
    <item>
     <POS>9</POS>
     <NAME>OBJVERSNO</NAME>
     <TYPE_KIND>N</TYPE_KIND>
     <LENGTH>5</LENGTH>
     <IS_KEY>X</IS_KEY>
    </item>
    <item>
     <POS>10</POS>
     <NAME>DELTA_MODE</NAME>
     <TYPE_KIND>C</TYPE_KIND>
     <LENGTH>2</LENGTH>
     <IS_KEY>X</IS_KEY>
    </item>
    <item>
     <POS>11</POS>
     <NAME>SRTF2</NAME>
     <TYPE_KIND>I</TYPE_KIND>
     <LENGTH>10</LENGTH>
     <IS_KEY>X</IS_KEY>
    </item>
    <item>
     <POS>12</POS>
     <NAME>CLUSTR</NAME>
     <TYPE_KIND>s</TYPE_KIND>
     <LENGTH>5</LENGTH>
    </item>
    <item>
     <POS>13</POS>
     <NAME>CLUSTD</NAME>
     <TYPE_KIND>X</TYPE_KIND>
     <LENGTH>2886</LENGTH>
    </item>
   </CWBCIDATAOBJ_field_catalog>
   <CWBCINSTATTR_field_catalog>
    <item>
     <POS>1</POS>
     <NAME>INSTA</NAME>
     <TYPE_KIND>C</TYPE_KIND>
     <LENGTH>10</LENGTH>
     <IS_KEY>X</IS_KEY>
    </item>
    <item>
     <POS>2</POS>
     <NAME>PAKID</NAME>
     <TYPE_KIND>C</TYPE_KIND>
     <LENGTH>10</LENGTH>
     <IS_KEY>X</IS_KEY>
    </item>
    <item>
     <POS>3</POS>
     <NAME>ALEID</NAME>
     <TYPE_KIND>N</TYPE_KIND>
     <LENGTH>10</LENGTH>
     <IS_KEY>X</IS_KEY>
    </item>
    <item>
     <POS>4</POS>
     <NAME>VERSNO</NAME>
     <TYPE_KIND>N</TYPE_KIND>
     <LENGTH>4</LENGTH>
     <IS_KEY>X</IS_KEY>
    </item>
    <item>
     <POS>5</POS>
     <NAME>ID</NAME>
     <TYPE_KIND>N</TYPE_KIND>
     <LENGTH>2</LENGTH>
     <IS_KEY>X</IS_KEY>
    </item>
    <item>
     <POS>6</POS>
     <NAME>VALUE</NAME>
     <TYPE_KIND>C</TYPE_KIND>
     <LENGTH>100</LENGTH>
    </item>
   </CWBCINSTATTR_field_catalog>
  </asx:values>
 </asx:abap>
</abapGit>
