<?xml version="1.0" encoding="utf-8"?>
<abapGit version="v1.0.0" serializer="ZCL_ABAPGIT_OBJECT_BY_SOBJ" serializer_version="1.0">
 <asx:abap xmlns:asx="http://www.sap.com/abapxml" version="1.0">
  <asx:values>
   <CWBCIHEAD>
    <CWBCIHEAD>
     <INSTA>0020751259</INSTA>
     <PAKID>6</PAKID>
     <ALEID>0000636828</ALEID>
     <VERSNO>0001</VERSNO>
     <FORMAT_ID>3</FORMAT_ID>
    </CWBCIHEAD>
   </CWBCIHEAD>
   <CWBCIHEAD_field_catalog>
    <item>
     <POS>1</POS>
     <NAME>INSTA</NAME>
     <TYPE_KIND>C</TYPE_KIND>
     <LENGTH>10</LENGTH>
     <IS_KEY>X</IS_KEY>
    </item>
    <item>
     <POS>2</POS>
     <NAME>PAKID</NAME>
     <TYPE_KIND>C</TYPE_KIND>
     <LENGTH>10</LENGTH>
     <IS_KEY>X</IS_KEY>
    </item>
    <item>
     <POS>3</POS>
     <NAME>ALEID</NAME>
     <TYPE_KIND>N</TYPE_KIND>
     <LENGTH>10</LENGTH>
     <IS_KEY>X</IS_KEY>
    </item>
    <item>
     <POS>4</POS>
     <NAME>VERSNO</NAME>
     <TYPE_KIND>N</TYPE_KIND>
     <LENGTH>4</LENGTH>
     <IS_KEY>X</IS_KEY>
    </item>
    <item>
     <POS>5</POS>
     <NAME>FORMAT_ID</NAME>
     <TYPE_KIND>I</TYPE_KIND>
     <LENGTH>10</LENGTH>
    </item>
    <item>
     <POS>6</POS>
     <NAME>INCOMPLETE</NAME>
     <TYPE_KIND>C</TYPE_KIND>
     <LENGTH>1</LENGTH>
    </item>
    <item>
     <POS>7</POS>
     <NAME>MANUAL_ACTIVITY</NAME>
     <TYPE_KIND>C</TYPE_KIND>
     <LENGTH>1</LENGTH>
    </item>
    <item>
     <POS>8</POS>
     <NAME>IS_TRANSPORTABLE</NAME>
     <TYPE_KIND>C</TYPE_KIND>
     <LENGTH>1</LENGTH>
    </item>
   </CWBCIHEAD_field_catalog>
   <CWBCIDATA_field_catalog>
    <item>
     <POS>1</POS>
     <NAME>RELID</NAME>
     <TYPE_KIND>C</TYPE_KIND>
     <LENGTH>2</LENGTH>
     <IS_KEY>X</IS_KEY>
    </item>
    <item>
     <POS>2</POS>
     <NAME>INSTA</NAME>
     <TYPE_KIND>C</TYPE_KIND>
     <LENGTH>10</LENGTH>
     <IS_KEY>X</IS_KEY>
    </item>
    <item>
     <POS>3</POS>
     <NAME>PAKID</NAME>
     <TYPE_KIND>C</TYPE_KIND>
     <LENGTH>10</LENGTH>
     <IS_KEY>X</IS_KEY>
    </item>
    <item>
     <POS>4</POS>
     <NAME>ALEID</NAME>
     <TYPE_KIND>N</TYPE_KIND>
     <LENGTH>10</LENGTH>
     <IS_KEY>X</IS_KEY>
    </item>
    <item>
     <POS>5</POS>
     <NAME>VERSNO</NAME>
     <TYPE_KIND>N</TYPE_KIND>
     <LENGTH>4</LENGTH>
     <IS_KEY>X</IS_KEY>
    </item>
    <item>
     <POS>6</POS>
     <NAME>SRTF2</NAME>
     <TYPE_KIND>I</TYPE_KIND>
     <LENGTH>10</LENGTH>
     <IS_KEY>X</IS_KEY>
    </item>
    <item>
     <POS>7</POS>
     <NAME>CLUSTR</NAME>
     <TYPE_KIND>s</TYPE_KIND>
     <LENGTH>5</LENGTH>
    </item>
    <item>
     <POS>8</POS>
     <NAME>CLUSTD</NAME>
     <TYPE_KIND>X</TYPE_KIND>
     <LENGTH>2886</LENGTH>
    </item>
   </CWBCIDATA_field_catalog>
   <CWBCIDPNDC>
    <CWBCIDPNDC>
     <INSTA>0020751259</INSTA>
     <PAKID>6</PAKID>
     <ALEID>0000636828</ALEID>
     <VERSNO>0001</VERSNO>
     <DEPTYPE>P</DEPTYPE>
     <CIINSTA_D>0020751258</CIINSTA_D>
     <CIPAKID_D>6</CIPAKID_D>
     <CIALEID_D>0000223102</CIALEID_D>
     <NTNUMM_D>0002501693</NTNUMM_D>
    </CWBCIDPNDC>
    <CWBCIDPNDC>
     <INSTA>0020751259</INSTA>
     <PAKID>6</PAKID>
     <ALEID>0000636828</ALEID>
     <VERSNO>0001</VERSNO>
     <DEPTYPE>P</DEPTYPE>
     <CIINSTA_D>0020751258</CIINSTA_D>
     <CIPAKID_D>6</CIPAKID_D>
     <CIALEID_D>0000243493</CIALEID_D>
     <NTNUMM_D>0002513407</NTNUMM_D>
    </CWBCIDPNDC>
    <CWBCIDPNDC>
     <INSTA>0020751259</INSTA>
     <PAKID>6</PAKID>
     <ALEID>0000636828</ALEID>
     <VERSNO>0001</VERSNO>
     <DEPTYPE>P</DEPTYPE>
     <CIINSTA_D>0020751258</CIINSTA_D>
     <CIPAKID_D>6</CIPAKID_D>
     <CIALEID_D>0000401383</CIALEID_D>
     <NTNUMM_D>0002686230</NTNUMM_D>
    </CWBCIDPNDC>
    <CWBCIDPNDC>
     <INSTA>0020751259</INSTA>
     <PAKID>6</PAKID>
     <ALEID>0000636828</ALEID>
     <VERSNO>0001</VERSNO>
     <DEPTYPE>P</DEPTYPE>
     <CIINSTA_D>0020751258</CIINSTA_D>
     <CIPAKID_D>6</CIPAKID_D>
     <CIALEID_D>0000483224</CIALEID_D>
     <NTNUMM_D>0002723714</NTNUMM_D>
    </CWBCIDPNDC>
    <CWBCIDPNDC>
     <INSTA>0020751259</INSTA>
     <PAKID>6</PAKID>
     <ALEID>0000636828</ALEID>
     <VERSNO>0001</VERSNO>
     <DEPTYPE>P</DEPTYPE>
     <CIINSTA_D>0020751259</CIINSTA_D>
     <CIPAKID_D>6</CIPAKID_D>
     <CIALEID_D>0000153253</CIALEID_D>
     <NTNUMM_D>0002423685</NTNUMM_D>
    </CWBCIDPNDC>
    <CWBCIDPNDC>
     <INSTA>0020751259</INSTA>
     <PAKID>6</PAKID>
     <ALEID>0000636828</ALEID>
     <VERSNO>0001</VERSNO>
     <DEPTYPE>P</DEPTYPE>
     <CIINSTA_D>0020751259</CIINSTA_D>
     <CIPAKID_D>6</CIPAKID_D>
     <CIALEID_D>0000249767</CIALEID_D>
     <NTNUMM_D>0002541016</NTNUMM_D>
    </CWBCIDPNDC>
    <CWBCIDPNDC>
     <INSTA>0020751259</INSTA>
     <PAKID>6</PAKID>
     <ALEID>0000636828</ALEID>
     <VERSNO>0001</VERSNO>
     <DEPTYPE>P</DEPTYPE>
     <CIINSTA_D>0020751259</CIINSTA_D>
     <CIPAKID_D>6</CIPAKID_D>
     <CIALEID_D>0000481176</CIALEID_D>
     <NTNUMM_D>0002736079</NTNUMM_D>
    </CWBCIDPNDC>
    <CWBCIDPNDC>
     <INSTA>0020751259</INSTA>
     <PAKID>6</PAKID>
     <ALEID>0000636828</ALEID>
     <VERSNO>0001</VERSNO>
     <DEPTYPE>P</DEPTYPE>
     <CIINSTA_D>0120031469</CIINSTA_D>
     <CIPAKID_D>6</CIPAKID_D>
     <CIALEID_D>0000889310</CIALEID_D>
     <NTNUMM_D>0001476571</NTNUMM_D>
    </CWBCIDPNDC>
    <CWBCIDPNDC>
     <INSTA>0020751259</INSTA>
     <PAKID>6</PAKID>
     <ALEID>0000636828</ALEID>
     <VERSNO>0001</VERSNO>
     <DEPTYPE>P</DEPTYPE>
     <CIINSTA_D>0120031469</CIINSTA_D>
     <CIPAKID_D>6</CIPAKID_D>
     <CIALEID_D>0000890923</CIALEID_D>
     <NTNUMM_D>0001477520</NTNUMM_D>
    </CWBCIDPNDC>
    <CWBCIDPNDC>
     <INSTA>0020751259</INSTA>
     <PAKID>6</PAKID>
     <ALEID>0000636828</ALEID>
     <VERSNO>0001</VERSNO>
     <DEPTYPE>P</DEPTYPE>
     <CIINSTA_D>0120031469</CIINSTA_D>
     <CIPAKID_D>6</CIPAKID_D>
     <CIALEID_D>0001549742</CIALEID_D>
     <NTNUMM_D>0002164993</NTNUMM_D>
    </CWBCIDPNDC>
    <CWBCIDPNDC>
     <INSTA>0020751259</INSTA>
     <PAKID>6</PAKID>
     <ALEID>0000636828</ALEID>
     <VERSNO>0001</VERSNO>
     <DEPTYPE>P</DEPTYPE>
     <CIINSTA_D>0120061532</CIINSTA_D>
     <CIPAKID_D>6</CIPAKID_D>
     <CIALEID_D>0001232441</CIALEID_D>
     <NTNUMM_D>0001483458</NTNUMM_D>
    </CWBCIDPNDC>
   </CWBCIDPNDC>
   <CWBCIDPNDC_field_catalog>
    <item>
     <POS>1</POS>
     <NAME>INSTA</NAME>
     <TYPE_KIND>C</TYPE_KIND>
     <LENGTH>10</LENGTH>
     <IS_KEY>X</IS_KEY>
    </item>
    <item>
     <POS>2</POS>
     <NAME>PAKID</NAME>
     <TYPE_KIND>C</TYPE_KIND>
     <LENGTH>10</LENGTH>
     <IS_KEY>X</IS_KEY>
    </item>
    <item>
     <POS>3</POS>
     <NAME>ALEID</NAME>
     <TYPE_KIND>N</TYPE_KIND>
     <LENGTH>10</LENGTH>
     <IS_KEY>X</IS_KEY>
    </item>
    <item>
     <POS>4</POS>
     <NAME>VERSNO</NAME>
     <TYPE_KIND>N</TYPE_KIND>
     <LENGTH>4</LENGTH>
     <IS_KEY>X</IS_KEY>
    </item>
    <item>
     <POS>5</POS>
     <NAME>DEPTYPE</NAME>
     <TYPE_KIND>C</TYPE_KIND>
     <LENGTH>1</LENGTH>
     <IS_KEY>X</IS_KEY>
    </item>
    <item>
     <POS>6</POS>
     <NAME>CIINSTA_D</NAME>
     <TYPE_KIND>C</TYPE_KIND>
     <LENGTH>10</LENGTH>
     <IS_KEY>X</IS_KEY>
    </item>
    <item>
     <POS>7</POS>
     <NAME>CIPAKID_D</NAME>
     <TYPE_KIND>C</TYPE_KIND>
     <LENGTH>10</LENGTH>
     <IS_KEY>X</IS_KEY>
    </item>
    <item>
     <POS>8</POS>
     <NAME>CIALEID_D</NAME>
     <TYPE_KIND>N</TYPE_KIND>
     <LENGTH>10</LENGTH>
     <IS_KEY>X</IS_KEY>
    </item>
    <item>
     <POS>9</POS>
     <NAME>NTNUMM_D</NAME>
     <TYPE_KIND>N</TYPE_KIND>
     <LENGTH>10</LENGTH>
     <IS_KEY>X</IS_KEY>
    </item>
   </CWBCIDPNDC_field_catalog>
   <CWBCIFIXED_field_catalog>
    <item>
     <POS>1</POS>
     <NAME>INSTA</NAME>
     <TYPE_KIND>C</TYPE_KIND>
     <LENGTH>10</LENGTH>
     <IS_KEY>X</IS_KEY>
    </item>
    <item>
     <POS>2</POS>
     <NAME>PAKID</NAME>
     <TYPE_KIND>C</TYPE_KIND>
     <LENGTH>10</LENGTH>
     <IS_KEY>X</IS_KEY>
    </item>
    <item>
     <POS>3</POS>
     <NAME>ALEID</NAME>
     <TYPE_KIND>N</TYPE_KIND>
     <LENGTH>10</LENGTH>
     <IS_KEY>X</IS_KEY>
    </item>
    <item>
     <POS>4</POS>
     <NAME>VERSNO</NAME>
     <TYPE_KIND>N</TYPE_KIND>
     <LENGTH>4</LENGTH>
     <IS_KEY>X</IS_KEY>
    </item>
    <item>
     <POS>5</POS>
     <NAME>DEPAKID_F</NAME>
     <TYPE_KIND>C</TYPE_KIND>
     <LENGTH>10</LENGTH>
     <IS_KEY>X</IS_KEY>
    </item>
    <item>
     <POS>6</POS>
     <NAME>DEALEID_F</NAME>
     <TYPE_KIND>N</TYPE_KIND>
     <LENGTH>10</LENGTH>
     <IS_KEY>X</IS_KEY>
    </item>
   </CWBCIFIXED_field_catalog>
   <CWBCIVALID>
    <CWBCIVALID>
     <INSTA>0020751259</INSTA>
     <PAKID>6</PAKID>
     <ALEID>0000636828</ALEID>
     <VERSNO>0001</VERSNO>
     <TRPAKID>6</TRPAKID>
     <TRTYPEID>P</TRTYPEID>
     <TRALSID>000045</TRALSID>
     <DEPAKID_LO>6</DEPAKID_LO>
     <DEALEID_LO>0000000345</DEALEID_LO>
     <DEPAKID_HI>6</DEPAKID_HI>
     <DEALEID_HI>0000000729</DEALEID_HI>
    </CWBCIVALID>
   </CWBCIVALID>
   <CWBCIVALID_field_catalog>
    <item>
     <POS>1</POS>
     <NAME>INSTA</NAME>
     <TYPE_KIND>C</TYPE_KIND>
     <LENGTH>10</LENGTH>
     <IS_KEY>X</IS_KEY>
    </item>
    <item>
     <POS>2</POS>
     <NAME>PAKID</NAME>
     <TYPE_KIND>C</TYPE_KIND>
     <LENGTH>10</LENGTH>
     <IS_KEY>X</IS_KEY>
    </item>
    <item>
     <POS>3</POS>
     <NAME>ALEID</NAME>
     <TYPE_KIND>N</TYPE_KIND>
     <LENGTH>10</LENGTH>
     <IS_KEY>X</IS_KEY>
    </item>
    <item>
     <POS>4</POS>
     <NAME>VERSNO</NAME>
     <TYPE_KIND>N</TYPE_KIND>
     <LENGTH>4</LENGTH>
     <IS_KEY>X</IS_KEY>
    </item>
    <item>
     <POS>5</POS>
     <NAME>TRPAKID</NAME>
     <TYPE_KIND>C</TYPE_KIND>
     <LENGTH>10</LENGTH>
     <IS_KEY>X</IS_KEY>
    </item>
    <item>
     <POS>6</POS>
     <NAME>TRTYPEID</NAME>
     <TYPE_KIND>C</TYPE_KIND>
     <LENGTH>1</LENGTH>
     <IS_KEY>X</IS_KEY>
    </item>
    <item>
     <POS>7</POS>
     <NAME>TRALSID</NAME>
     <TYPE_KIND>N</TYPE_KIND>
     <LENGTH>6</LENGTH>
     <IS_KEY>X</IS_KEY>
    </item>
    <item>
     <POS>8</POS>
     <NAME>DEPAKID_LO</NAME>
     <TYPE_KIND>C</TYPE_KIND>
     <LENGTH>10</LENGTH>
     <IS_KEY>X</IS_KEY>
    </item>
    <item>
     <POS>9</POS>
     <NAME>DEALEID_LO</NAME>
     <TYPE_KIND>N</TYPE_KIND>
     <LENGTH>10</LENGTH>
     <IS_KEY>X</IS_KEY>
    </item>
    <item>
     <POS>10</POS>
     <NAME>DEPAKID_HI</NAME>
     <TYPE_KIND>C</TYPE_KIND>
     <LENGTH>10</LENGTH>
     <IS_KEY>X</IS_KEY>
    </item>
    <item>
     <POS>11</POS>
     <NAME>DEALEID_HI</NAME>
     <TYPE_KIND>N</TYPE_KIND>
     <LENGTH>10</LENGTH>
     <IS_KEY>X</IS_KEY>
    </item>
   </CWBCIVALID_field_catalog>
   <CWBCIOBJ>
    <CWBCIOBJ>
     <INSTA>0020751259</INSTA>
     <PAKID>6</PAKID>
     <ALEID>0000636828</ALEID>
     <VERSNO>0001</VERSNO>
     <PGMID>LIMU</PGMID>
     <OBJECT>METH</OBJECT>
     <OBJ_NAME>CL_ISHMED_OBJTY_DISP_DOC_PDF  BUILD_CONTROLS</OBJ_NAME>
     <TRPGMID>R3TR</TRPGMID>
     <TROBJECT>CLAS</TROBJECT>
     <TROBJ_NAME>CL_ISHMED_OBJTY_DISP_DOC_PDF</TROBJ_NAME>
    </CWBCIOBJ>
   </CWBCIOBJ>
   <CWBCIOBJ_field_catalog>
    <item>
     <POS>1</POS>
     <NAME>INSTA</NAME>
     <TYPE_KIND>C</TYPE_KIND>
     <LENGTH>10</LENGTH>
     <IS_KEY>X</IS_KEY>
    </item>
    <item>
     <POS>2</POS>
     <NAME>PAKID</NAME>
     <TYPE_KIND>C</TYPE_KIND>
     <LENGTH>10</LENGTH>
     <IS_KEY>X</IS_KEY>
    </item>
    <item>
     <POS>3</POS>
     <NAME>ALEID</NAME>
     <TYPE_KIND>N</TYPE_KIND>
     <LENGTH>10</LENGTH>
     <IS_KEY>X</IS_KEY>
    </item>
    <item>
     <POS>4</POS>
     <NAME>VERSNO</NAME>
     <TYPE_KIND>N</TYPE_KIND>
     <LENGTH>4</LENGTH>
     <IS_KEY>X</IS_KEY>
    </item>
    <item>
     <POS>5</POS>
     <NAME>PGMID</NAME>
     <TYPE_KIND>C</TYPE_KIND>
     <LENGTH>4</LENGTH>
     <IS_KEY>X</IS_KEY>
    </item>
    <item>
     <POS>6</POS>
     <NAME>OBJECT</NAME>
     <TYPE_KIND>C</TYPE_KIND>
     <LENGTH>4</LENGTH>
     <IS_KEY>X</IS_KEY>
    </item>
    <item>
     <POS>7</POS>
     <NAME>OBJ_NAME</NAME>
     <TYPE_KIND>C</TYPE_KIND>
     <LENGTH>120</LENGTH>
     <IS_KEY>X</IS_KEY>
    </item>
    <item>
     <POS>8</POS>
     <NAME>TRPGMID</NAME>
     <TYPE_KIND>C</TYPE_KIND>
     <LENGTH>4</LENGTH>
    </item>
    <item>
     <POS>9</POS>
     <NAME>TROBJECT</NAME>
     <TYPE_KIND>C</TYPE_KIND>
     <LENGTH>4</LENGTH>
    </item>
    <item>
     <POS>10</POS>
     <NAME>TROBJ_NAME</NAME>
     <TYPE_KIND>C</TYPE_KIND>
     <LENGTH>40</LENGTH>
    </item>
   </CWBCIOBJ_field_catalog>
   <CWBCICATTR_field_catalog>
    <item>
     <POS>1</POS>
     <NAME>INSTA</NAME>
     <TYPE_KIND>C</TYPE_KIND>
     <LENGTH>10</LENGTH>
     <IS_KEY>X</IS_KEY>
    </item>
    <item>
     <POS>2</POS>
     <NAME>PAKID</NAME>
     <TYPE_KIND>C</TYPE_KIND>
     <LENGTH>10</LENGTH>
     <IS_KEY>X</IS_KEY>
    </item>
    <item>
     <POS>3</POS>
     <NAME>ALEID</NAME>
     <TYPE_KIND>N</TYPE_KIND>
     <LENGTH>10</LENGTH>
     <IS_KEY>X</IS_KEY>
    </item>
    <item>
     <POS>4</POS>
     <NAME>VERSNO</NAME>
     <TYPE_KIND>N</TYPE_KIND>
     <LENGTH>4</LENGTH>
     <IS_KEY>X</IS_KEY>
    </item>
    <item>
     <POS>5</POS>
     <NAME>CONFIRMED</NAME>
     <TYPE_KIND>C</TYPE_KIND>
     <LENGTH>1</LENGTH>
    </item>
    <item>
     <POS>6</POS>
     <NAME>CISTATUS</NAME>
     <TYPE_KIND>C</TYPE_KIND>
     <LENGTH>1</LENGTH>
    </item>
    <item>
     <POS>7</POS>
     <NAME>CONFIRM_ACTIVITY</NAME>
     <TYPE_KIND>C</TYPE_KIND>
     <LENGTH>1</LENGTH>
    </item>
   </CWBCICATTR_field_catalog>
   <CWBCIINVLD_field_catalog>
    <item>
     <POS>1</POS>
     <NAME>INSTA</NAME>
     <TYPE_KIND>C</TYPE_KIND>
     <LENGTH>10</LENGTH>
     <IS_KEY>X</IS_KEY>
    </item>
    <item>
     <POS>2</POS>
     <NAME>PAKID</NAME>
     <TYPE_KIND>C</TYPE_KIND>
     <LENGTH>10</LENGTH>
     <IS_KEY>X</IS_KEY>
    </item>
    <item>
     <POS>3</POS>
     <NAME>ALEID</NAME>
     <TYPE_KIND>N</TYPE_KIND>
     <LENGTH>10</LENGTH>
     <IS_KEY>X</IS_KEY>
    </item>
    <item>
     <POS>4</POS>
     <NAME>VERSNO</NAME>
     <TYPE_KIND>N</TYPE_KIND>
     <LENGTH>4</LENGTH>
     <IS_KEY>X</IS_KEY>
    </item>
    <item>
     <POS>5</POS>
     <NAME>TRPAKID</NAME>
     <TYPE_KIND>C</TYPE_KIND>
     <LENGTH>10</LENGTH>
     <IS_KEY>X</IS_KEY>
    </item>
    <item>
     <POS>6</POS>
     <NAME>TRTYPEID</NAME>
     <TYPE_KIND>C</TYPE_KIND>
     <LENGTH>1</LENGTH>
     <IS_KEY>X</IS_KEY>
    </item>
    <item>
     <POS>7</POS>
     <NAME>TRALSID</NAME>
     <TYPE_KIND>N</TYPE_KIND>
     <LENGTH>6</LENGTH>
     <IS_KEY>X</IS_KEY>
    </item>
    <item>
     <POS>8</POS>
     <NAME>DEPAKID_LO</NAME>
     <TYPE_KIND>C</TYPE_KIND>
     <LENGTH>10</LENGTH>
     <IS_KEY>X</IS_KEY>
    </item>
    <item>
     <POS>9</POS>
     <NAME>DEALEID_LO</NAME>
     <TYPE_KIND>N</TYPE_KIND>
     <LENGTH>10</LENGTH>
     <IS_KEY>X</IS_KEY>
    </item>
    <item>
     <POS>10</POS>
     <NAME>DEPAKID_HI</NAME>
     <TYPE_KIND>C</TYPE_KIND>
     <LENGTH>10</LENGTH>
     <IS_KEY>X</IS_KEY>
    </item>
    <item>
     <POS>11</POS>
     <NAME>DEALEID_HI</NAME>
     <TYPE_KIND>N</TYPE_KIND>
     <LENGTH>10</LENGTH>
     <IS_KEY>X</IS_KEY>
    </item>
   </CWBCIINVLD_field_catalog>
   <CWBCIDATAOBJ>
    <CWBCIDATAOBJ>
     <RELID>CI</RELID>
     <INSTA>0020751259</INSTA>
     <PAKID>6</PAKID>
     <ALEID>0000636828</ALEID>
     <VERSNO>0001</VERSNO>
     <PGMID>LIMU</PGMID>
     <OBJTYPE>METH</OBJTYPE>
     <OBJNAME>CL_ISHMED_OBJTY_DISP_DOC_PDF  BUILD_CONTROLS</OBJNAME>
     <OBJVERSNO>99989</OBJVERSNO>
     <DELTA_MODE>O</DELTA_MODE>
     <CLUSTR>872</CLUSTR>
     <CLUSTD>/wYCAQICgAA0MTAzAAAAANQGAAASH50Crazqctu4gbAegjYH6AEEIa9r7sqSWgsjBhRJy1tzf0Jy
hdXTQkndNkBiG5ET50K9THupzpC7kpMUCLqQxO+bPw5nZqkffxrh85x+no3+41EjMfL4/Xs0+uEv
ePn5/bvxp5sPh7d3t6tJdpZOxje3b+5+e3v7x2ry8eH35JfJSw77w+fl/vX+/itL9L09LFG5mvz5
8HC/ZOzx8fHssL8/e3P3npEDWkyi+6f9u483Bw5tUpiuVcILDmItaq9bzzgUylQbDtu2qFQeoXWX
RmxQV61/7fyu1lwa4YAdaVCUoiBFl7urQqsORX7XqdzVnapkV6vL6BDMwDXr6FpofwXsSIPiu5HG
43WTG9XJqvS2Mi4GiJHz0odQLEISUua1tsLnVcmFMZjIkUIh8rKrbbUJDtI0iuzx8IMrQSPKTdPj
xmnL5TxdTGfpFNhRFJRYTs2nafZzkl4k04uoDsKg9jmmmC2W2Ww5zaIyiEBIn29jzkfY1BsrQja1
1XhWawOsfFeVZsdbYCdCxh2GCwkLe42Lq0VDRmEFb68xANezV9fpIltkmFovCoYYPviyJ31n/Sh4
q3I0a/v1NA7f7dNqJYs0xYP2TX9lWnTTyreUWFhhK6w0RCMAhaNoOLY0AuSl4OoFcQRAk4cx+g5X
UjaWOPZf8jzMgcRq1jFEWMFpSb2TmAR3ogYWEEhsC7YqnSfpNJnOUEwCaEgp59n8PJvNgQUKTbTN
LpI0SzK0DQLYalvyFJ9zHIRAwOitwc2s84LeJluIUtEuwCIEayqhuEIeAFzmbe3p/BGAc5oc3TBJ
xy2jBFycoRR7iJtGBvk31lEC+RfWkYGhUiJQL7BGA4FGyistaXLY0Go2rE/vioC9CIp6U+SK23Nv
cRgDpqtAS3+6IYj8//uBJrNsCiqElW7nvO57d6IgGn9V2SjuMVkrXXMbDAmB0lvKxfGyslj1I4WN
Lvs5xkHskcQ3KmQ8xuSPBN8o3NHSJUCNe8JoAhyeOj1LwwAQhlpcl9VQSzwSjsLa+B2Fr4q6KnXp
ee4SvPZOHKTVRgun+WxxjoqBYfqmz81bUTrjfbil0QD7i1WM85eET/AbxBAyiHfPFyYncW8iLzds
6HHfV/b0j4INfzr8n2f/Ag==</CLUSTD>
    </CWBCIDATAOBJ>
    <CWBCIDATAOBJ>
     <RELID>CI</RELID>
     <INSTA>0020751259</INSTA>
     <PAKID>6</PAKID>
     <ALEID>0000636828</ALEID>
     <VERSNO>0001</VERSNO>
     <PGMID>LIMU</PGMID>
     <OBJTYPE>METH</OBJTYPE>
     <OBJNAME>CL_ISHMED_OBJTY_DISP_DOC_PDF  BUILD_CONTROLS</OBJNAME>
     <OBJVERSNO>99990</OBJVERSNO>
     <CLUSTR>718</CLUSTR>
     <CLUSTD>/wYCAQICgAA0MTAzAAAAAIgHAAASH50Cu7qq220ahsK5QIIH4I4bqxdMGuvcH/bT4XpK6rM1LD9V
4rJNQrKy1nSBNKnabN244h14K3gLngQnoWOUVHTiAnEuHPv4Oyefz4/9+Kmm5Ek2PNNKxNA62qka
mSY0X+Oap/WVhqvR0yDXdjRXfUHNstFSe7r2RdMevyCHN+MIXcvpLEzidqW+XasgGQ+SYRiP2pWr
9F11v3JISTC7OQgugskSUtnGswO12a5cpunkAOP5fL49Cybbg2SMMwOFqBTm10F0JWeUnFVtS3Rc
BoKBxXVKuqAz8ChxLUZJ79g2GbVMu09wMSeu8Zqf94DawLsEL1aZ2tFtoB1LmH7XBibyLcFMvyeY
2xE9doSQ0Tctpn7ncM+1/Nw8tyJvwPMdl9ZqteYuwT9WhIHPTUfnputgqtAZJQdO/wmvWm0lr5wS
XgTO5zoHGxwuejrn4Dm+0nVODXG3QQl3T8BRCo++zSROhBxP0ltxESWDDzOcCcE/QQQvO/iDQ5Xv
sYzTmQhHcTKVw7/3OJRRGgjlbBxE4ce1POKySOSlZlhu56QouEVwlvWUmEzFFqzcge6d/wpf1lNi
mY5KTb3VILiYkiydcKaI6Ibe42e8sbOTw4CiXMBh5tF2DleZxvdRpRZg+bAmfBN5bAupaqs2W61G
fUs18bDUEt+RVMcADmW+NnNHu/v7zSYy5CiM0bdPn9FUjpNrOUTzML0sAK3WThM5SSpRY6+5W9tr
ISNc/3SmaoNIBJNJFA6CVF0qqI02erqn28w96W+Us1+QNh0fvLJIF9z3mvX6y4L7uoQUnVAMgiiS
04IId73jjQdkyweOurrDLPDQSCQX7+UgTW8nsvp8lL66DOJhJEUwyA965HpoLNf2/ZC6uX9+WFED
/1XGF5nGK9oQl3QsXtHhuOQywL89SPj+c4UXTx/9+ug7</CLUSTD>
    </CWBCIDATAOBJ>
    <CWBCIDATAOBJ>
     <RELID>CI</RELID>
     <INSTA>0020751259</INSTA>
     <PAKID>6</PAKID>
     <ALEID>0000636828</ALEID>
     <VERSNO>0001</VERSNO>
     <PGMID>LIMU</PGMID>
     <OBJTYPE>METH</OBJTYPE>
     <OBJNAME>CL_ISHMED_OBJTY_DISP_DOC_PDF  BUILD_CONTROLS</OBJNAME>
     <OBJVERSNO>99990</OBJVERSNO>
     <DELTA_MODE>N</DELTA_MODE>
     <CLUSTR>872</CLUSTR>
     <CLUSTD>/wYCAQICgAA0MTAzAAAAANQGAAASH50CVFZ1uW3cQFgPQZsD9ACCkNc1dyVZjYURA4qk5a25PyG5
wuppoaRuGyCxjcqJc6Fepr1UZ8hdyWkDBBFs8ftmvpkdcmapH38a4ec5fT0bfeWjRmLk8f/v0eiH
v+DV5w/vx59u/jy8u7tdTbKzdDK+uX179+u7299Xk48PvyUvJ6847A+fl/s3+/v/KDH29rBE52ry
x8PD/ZKxx8fHs8P+/uzt3QdGAaiYxPBP+/cfbw4c2qQwXauEFxzEWtRet55xKJSpNhy2bVGpPELr
Lo3YoK9a/9L5Xa25NMIBO9LgKEVBji53V4VWHZr8rlO5qztVya5WlzEgyMA16xhaaH8F7EiD45uZ
xuN1kxvVyar0tjIuJoiZ89KHVCxCMlLltbbC51XJhTFYyJFCIfKyq221CQHSNIr0uPkhlKAR5abp
ceO05fI8XUzn6RTY0RSceJyaT9Ps5yS9SKYX0R2Mwe1zLDFbLLP5cppFZzCBkD7fxpqPsKk3VoRq
aqtxr9YGWPmuKs2Ot8BOhMQdpgsFC3uNi6tFQ6KwgrfXmIDr+evrdJEtMiytNwUhpg+x7EnfWT8K
3qocZW2/nsbhm31arWSRprjRvumvTYthWvmWCgsrbIWVhmgEoHAUDceWRoC8FFy9II4AaPIwR9/h
SsrGEsf+S56HOZB4mnVMEVZwWlLvJBbBnaiBBQQS24KtSs+TdJpM52gmAzTkxPaev5ydz4AFCk3U
ZhdJliXTFM1Bu9W25Cl+ZqgMBIzeGnyYdV7Q22QLUSp6CrAIwZpKKK6QBwCXeVt72n8E4JymQDdM
0vGR0QIuzlA2m1MPI4P8f+pogfwLdWRg6CgRqBd4RgOBRsorLWly2NBqNqxP74qAvQiOelPkituZ
tziMAdNVoKU/3RBEvv9+oMksm4IOwkq3c173vTtREI2/qmw095jUStfcBiEhUHpLtTheVhZP/Uhh
o8t+jnEQeyTxjQoVj7H4I8E3Cp9o6RKgxj1hNAEOd52epWEACEMtrstqOEvcEo7C2vgdpa+Kuip1
6XnuErz2Thyk1UYLp/l8gbN0ZFi+6WvzVpTOeB9uaRRgf/EU4/wl4S/EDWYIFcS75wvJydxL5OWG
DT3u+8qe/lCw4UeH//PsXw==</CLUSTD>
    </CWBCIDATAOBJ>
   </CWBCIDATAOBJ>
   <CWBCIDATAOBJ_field_catalog>
    <item>
     <POS>1</POS>
     <NAME>RELID</NAME>
     <TYPE_KIND>C</TYPE_KIND>
     <LENGTH>2</LENGTH>
     <IS_KEY>X</IS_KEY>
    </item>
    <item>
     <POS>2</POS>
     <NAME>INSTA</NAME>
     <TYPE_KIND>C</TYPE_KIND>
     <LENGTH>10</LENGTH>
     <IS_KEY>X</IS_KEY>
    </item>
    <item>
     <POS>3</POS>
     <NAME>PAKID</NAME>
     <TYPE_KIND>C</TYPE_KIND>
     <LENGTH>10</LENGTH>
     <IS_KEY>X</IS_KEY>
    </item>
    <item>
     <POS>4</POS>
     <NAME>ALEID</NAME>
     <TYPE_KIND>N</TYPE_KIND>
     <LENGTH>10</LENGTH>
     <IS_KEY>X</IS_KEY>
    </item>
    <item>
     <POS>5</POS>
     <NAME>VERSNO</NAME>
     <TYPE_KIND>N</TYPE_KIND>
     <LENGTH>4</LENGTH>
     <IS_KEY>X</IS_KEY>
    </item>
    <item>
     <POS>6</POS>
     <NAME>PGMID</NAME>
     <TYPE_KIND>C</TYPE_KIND>
     <LENGTH>4</LENGTH>
     <IS_KEY>X</IS_KEY>
    </item>
    <item>
     <POS>7</POS>
     <NAME>OBJTYPE</NAME>
     <TYPE_KIND>C</TYPE_KIND>
     <LENGTH>4</LENGTH>
     <IS_KEY>X</IS_KEY>
    </item>
    <item>
     <POS>8</POS>
     <NAME>OBJNAME</NAME>
     <TYPE_KIND>C</TYPE_KIND>
     <LENGTH>120</LENGTH>
     <IS_KEY>X</IS_KEY>
    </item>
    <item>
     <POS>9</POS>
     <NAME>OBJVERSNO</NAME>
     <TYPE_KIND>N</TYPE_KIND>
     <LENGTH>5</LENGTH>
     <IS_KEY>X</IS_KEY>
    </item>
    <item>
     <POS>10</POS>
     <NAME>DELTA_MODE</NAME>
     <TYPE_KIND>C</TYPE_KIND>
     <LENGTH>2</LENGTH>
     <IS_KEY>X</IS_KEY>
    </item>
    <item>
     <POS>11</POS>
     <NAME>SRTF2</NAME>
     <TYPE_KIND>I</TYPE_KIND>
     <LENGTH>10</LENGTH>
     <IS_KEY>X</IS_KEY>
    </item>
    <item>
     <POS>12</POS>
     <NAME>CLUSTR</NAME>
     <TYPE_KIND>s</TYPE_KIND>
     <LENGTH>5</LENGTH>
    </item>
    <item>
     <POS>13</POS>
     <NAME>CLUSTD</NAME>
     <TYPE_KIND>X</TYPE_KIND>
     <LENGTH>2886</LENGTH>
    </item>
   </CWBCIDATAOBJ_field_catalog>
   <CWBCINSTATTR_field_catalog>
    <item>
     <POS>1</POS>
     <NAME>INSTA</NAME>
     <TYPE_KIND>C</TYPE_KIND>
     <LENGTH>10</LENGTH>
     <IS_KEY>X</IS_KEY>
    </item>
    <item>
     <POS>2</POS>
     <NAME>PAKID</NAME>
     <TYPE_KIND>C</TYPE_KIND>
     <LENGTH>10</LENGTH>
     <IS_KEY>X</IS_KEY>
    </item>
    <item>
     <POS>3</POS>
     <NAME>ALEID</NAME>
     <TYPE_KIND>N</TYPE_KIND>
     <LENGTH>10</LENGTH>
     <IS_KEY>X</IS_KEY>
    </item>
    <item>
     <POS>4</POS>
     <NAME>VERSNO</NAME>
     <TYPE_KIND>N</TYPE_KIND>
     <LENGTH>4</LENGTH>
     <IS_KEY>X</IS_KEY>
    </item>
    <item>
     <POS>5</POS>
     <NAME>ID</NAME>
     <TYPE_KIND>N</TYPE_KIND>
     <LENGTH>2</LENGTH>
     <IS_KEY>X</IS_KEY>
    </item>
    <item>
     <POS>6</POS>
     <NAME>VALUE</NAME>
     <TYPE_KIND>C</TYPE_KIND>
     <LENGTH>100</LENGTH>
    </item>
   </CWBCINSTATTR_field_catalog>
  </asx:values>
 </asx:abap>
</abapGit>
