<?xml version="1.0" encoding="utf-8"?>
<abapGit version="v1.0.0" serializer="ZCL_ABAPGIT_OBJECT_BY_SOBJ" serializer_version="1.0">
 <asx:abap xmlns:asx="http://www.sap.com/abapxml" version="1.0">
  <asx:values>
   <SXS_ATTR>
    <SXS_ATTR>
     <EXIT_NAME>N1_CONNECTIVITY</EXIT_NAME>
     <DEVCLASS>N1BASE</DEVCLASS>
     <MST_LANG>D</MST_LANG>
     <DOKU_ID>N1_CONNECTIVITY</DOKU_ID>
     <COC_CLNAME>CL_EX_CC_N1_CONNECTIVITY</COC_CLNAME>
     <UNAME>SAP</UNAME>
     <UDATE>2005-04-07</UDATE>
     <UTIME>08:10:38</UTIME>
    </SXS_ATTR>
   </SXS_ATTR>
   <SXS_ATTR_field_catalog>
    <item>
     <POS>1</POS>
     <NAME>EXIT_NAME</NAME>
     <TYPE_KIND>C</TYPE_KIND>
     <LENGTH>20</LENGTH>
     <IS_KEY>X</IS_KEY>
    </item>
    <item>
     <POS>2</POS>
     <NAME>VERSION</NAME>
     <TYPE_KIND>C</TYPE_KIND>
     <LENGTH>6</LENGTH>
    </item>
    <item>
     <POS>3</POS>
     <NAME>FLT_TYPE</NAME>
     <TYPE_KIND>C</TYPE_KIND>
     <LENGTH>30</LENGTH>
    </item>
    <item>
     <POS>4</POS>
     <NAME>FLT_EXT</NAME>
     <TYPE_KIND>C</TYPE_KIND>
     <LENGTH>1</LENGTH>
    </item>
    <item>
     <POS>5</POS>
     <NAME>MLTP_USE</NAME>
     <TYPE_KIND>C</TYPE_KIND>
     <LENGTH>1</LENGTH>
    </item>
    <item>
     <POS>6</POS>
     <NAME>DEVCLASS</NAME>
     <TYPE_KIND>C</TYPE_KIND>
     <LENGTH>30</LENGTH>
    </item>
    <item>
     <POS>7</POS>
     <NAME>MST_LANG</NAME>
     <TYPE_KIND>C</TYPE_KIND>
     <LENGTH>1</LENGTH>
    </item>
    <item>
     <POS>8</POS>
     <NAME>DOKU_ID</NAME>
     <TYPE_KIND>C</TYPE_KIND>
     <LENGTH>60</LENGTH>
    </item>
    <item>
     <POS>9</POS>
     <NAME>DEF_CLNAME</NAME>
     <TYPE_KIND>C</TYPE_KIND>
     <LENGTH>30</LENGTH>
    </item>
    <item>
     <POS>10</POS>
     <NAME>EXM_CLNAME</NAME>
     <TYPE_KIND>C</TYPE_KIND>
     <LENGTH>30</LENGTH>
    </item>
    <item>
     <POS>11</POS>
     <NAME>COC_CLNAME</NAME>
     <TYPE_KIND>C</TYPE_KIND>
     <LENGTH>30</LENGTH>
    </item>
    <item>
     <POS>12</POS>
     <NAME>UNAME</NAME>
     <TYPE_KIND>C</TYPE_KIND>
     <LENGTH>12</LENGTH>
    </item>
    <item>
     <POS>13</POS>
     <NAME>UDATE</NAME>
     <TYPE_KIND>D</TYPE_KIND>
     <LENGTH>8</LENGTH>
    </item>
    <item>
     <POS>14</POS>
     <NAME>UTIME</NAME>
     <TYPE_KIND>T</TYPE_KIND>
     <LENGTH>6</LENGTH>
    </item>
    <item>
     <POS>15</POS>
     <NAME>INTERNAL</NAME>
     <TYPE_KIND>C</TYPE_KIND>
     <LENGTH>1</LENGTH>
    </item>
    <item>
     <POS>16</POS>
     <NAME>MIG_ENHSPOTNAME</NAME>
     <TYPE_KIND>C</TYPE_KIND>
     <LENGTH>30</LENGTH>
    </item>
    <item>
     <POS>17</POS>
     <NAME>MIG_BADI_NAME</NAME>
     <TYPE_KIND>C</TYPE_KIND>
     <LENGTH>30</LENGTH>
    </item>
   </SXS_ATTR_field_catalog>
   <SXS_ATTRT>
    <SXS_ATTRT>
     <EXIT_NAME>N1_CONNECTIVITY</EXIT_NAME>
     <SPRSL>E</SPRSL>
     <TEXT>External Communication (Data Interchange)</TEXT>
    </SXS_ATTRT>
   </SXS_ATTRT>
   <SXS_ATTRT_field_catalog>
    <item>
     <POS>1</POS>
     <NAME>EXIT_NAME</NAME>
     <TYPE_KIND>C</TYPE_KIND>
     <LENGTH>20</LENGTH>
     <IS_KEY>X</IS_KEY>
    </item>
    <item>
     <POS>2</POS>
     <NAME>SPRSL</NAME>
     <TYPE_KIND>C</TYPE_KIND>
     <LENGTH>1</LENGTH>
     <IS_KEY>X</IS_KEY>
    </item>
    <item>
     <POS>3</POS>
     <NAME>TEXT</NAME>
     <TYPE_KIND>C</TYPE_KIND>
     <LENGTH>60</LENGTH>
    </item>
   </SXS_ATTRT_field_catalog>
   <SXS_STAT>
    <SXS_STAT>
     <EXIT_NAME>N1_CONNECTIVITY</EXIT_NAME>
     <METH_NAME>EXIT_CHECK</METH_NAME>
     <UUID>Gb8uoVri9NhX00002XLK0G</UUID>
    </SXS_STAT>
    <SXS_STAT>
     <EXIT_NAME>N1_CONNECTIVITY</EXIT_NAME>
     <METH_NAME>EXIT_EXPORT</METH_NAME>
     <UUID>Gb8up}ri9NhX00002XLK0G</UUID>
    </SXS_STAT>
    <SXS_STAT>
     <EXIT_NAME>N1_CONNECTIVITY</EXIT_NAME>
     <METH_NAME>EXIT_IMPORT_CORDER</METH_NAME>
     <UUID>Gb8urVri9NhX00002XLK0G</UUID>
    </SXS_STAT>
   </SXS_STAT>
   <SXS_STAT_field_catalog>
    <item>
     <POS>1</POS>
     <NAME>EXIT_NAME</NAME>
     <TYPE_KIND>C</TYPE_KIND>
     <LENGTH>20</LENGTH>
     <IS_KEY>X</IS_KEY>
    </item>
    <item>
     <POS>2</POS>
     <NAME>METH_NAME</NAME>
     <TYPE_KIND>C</TYPE_KIND>
     <LENGTH>30</LENGTH>
     <IS_KEY>X</IS_KEY>
    </item>
    <item>
     <POS>3</POS>
     <NAME>UUID</NAME>
     <TYPE_KIND>C</TYPE_KIND>
     <LENGTH>22</LENGTH>
    </item>
   </SXS_STAT_field_catalog>
   <SXS_SCRN_field_catalog>
    <item>
     <POS>1</POS>
     <NAME>EXIT_NAME</NAME>
     <TYPE_KIND>C</TYPE_KIND>
     <LENGTH>20</LENGTH>
     <IS_KEY>X</IS_KEY>
    </item>
    <item>
     <POS>2</POS>
     <NAME>SCR_A_PROG</NAME>
     <TYPE_KIND>C</TYPE_KIND>
     <LENGTH>40</LENGTH>
     <IS_KEY>X</IS_KEY>
    </item>
    <item>
     <POS>3</POS>
     <NAME>SCR_A_NUM</NAME>
     <TYPE_KIND>N</TYPE_KIND>
     <LENGTH>4</LENGTH>
     <IS_KEY>X</IS_KEY>
    </item>
    <item>
     <POS>4</POS>
     <NAME>SCR_A_SSCR</NAME>
     <TYPE_KIND>C</TYPE_KIND>
     <LENGTH>30</LENGTH>
     <IS_KEY>X</IS_KEY>
    </item>
   </SXS_SCRN_field_catalog>
   <SXS_FCODE_field_catalog>
    <item>
     <POS>1</POS>
     <NAME>EXIT_NAME</NAME>
     <TYPE_KIND>C</TYPE_KIND>
     <LENGTH>20</LENGTH>
     <IS_KEY>X</IS_KEY>
    </item>
    <item>
     <POS>2</POS>
     <NAME>GUI_PROG</NAME>
     <TYPE_KIND>C</TYPE_KIND>
     <LENGTH>40</LENGTH>
     <IS_KEY>X</IS_KEY>
    </item>
    <item>
     <POS>3</POS>
     <NAME>GUI_CODE</NAME>
     <TYPE_KIND>C</TYPE_KIND>
     <LENGTH>20</LENGTH>
     <IS_KEY>X</IS_KEY>
    </item>
   </SXS_FCODE_field_catalog>
   <SXS_TABLE_field_catalog>
    <item>
     <POS>1</POS>
     <NAME>EXIT_NAME</NAME>
     <TYPE_KIND>C</TYPE_KIND>
     <LENGTH>20</LENGTH>
     <IS_KEY>X</IS_KEY>
    </item>
    <item>
     <POS>2</POS>
     <NAME>TABNAME</NAME>
     <TYPE_KIND>C</TYPE_KIND>
     <LENGTH>30</LENGTH>
     <IS_KEY>X</IS_KEY>
    </item>
   </SXS_TABLE_field_catalog>
   <SXS_INTER>
    <SXS_INTER>
     <EXIT_NAME>N1_CONNECTIVITY</EXIT_NAME>
     <INTER_NAME>IF_EX_N1_CONNECTIVITY</INTER_NAME>
    </SXS_INTER>
   </SXS_INTER>
   <SXS_INTER_field_catalog>
    <item>
     <POS>1</POS>
     <NAME>EXIT_NAME</NAME>
     <TYPE_KIND>C</TYPE_KIND>
     <LENGTH>20</LENGTH>
     <IS_KEY>X</IS_KEY>
    </item>
    <item>
     <POS>2</POS>
     <NAME>INTER_NAME</NAME>
     <TYPE_KIND>C</TYPE_KIND>
     <LENGTH>30</LENGTH>
     <IS_KEY>X</IS_KEY>
    </item>
   </SXS_INTER_field_catalog>
   <SXS_COCO_field_catalog>
    <item>
     <POS>1</POS>
     <NAME>EXIT_NAME</NAME>
     <TYPE_KIND>C</TYPE_KIND>
     <LENGTH>20</LENGTH>
     <IS_KEY>X</IS_KEY>
    </item>
    <item>
     <POS>2</POS>
     <NAME>COCO_OUTER</NAME>
     <TYPE_KIND>C</TYPE_KIND>
     <LENGTH>40</LENGTH>
     <IS_KEY>X</IS_KEY>
    </item>
    <item>
     <POS>3</POS>
     <NAME>NODE_ID</NAME>
     <TYPE_KIND>C</TYPE_KIND>
     <LENGTH>59</LENGTH>
     <IS_KEY>X</IS_KEY>
    </item>
   </SXS_COCO_field_catalog>
   <SXS_SCRNT_field_catalog>
    <item>
     <POS>1</POS>
     <NAME>EXIT_NAME</NAME>
     <TYPE_KIND>C</TYPE_KIND>
     <LENGTH>20</LENGTH>
     <IS_KEY>X</IS_KEY>
    </item>
    <item>
     <POS>2</POS>
     <NAME>SPRSL</NAME>
     <TYPE_KIND>C</TYPE_KIND>
     <LENGTH>1</LENGTH>
     <IS_KEY>X</IS_KEY>
    </item>
    <item>
     <POS>3</POS>
     <NAME>SCR_A_PROG</NAME>
     <TYPE_KIND>C</TYPE_KIND>
     <LENGTH>40</LENGTH>
     <IS_KEY>X</IS_KEY>
    </item>
    <item>
     <POS>4</POS>
     <NAME>SCR_A_NUM</NAME>
     <TYPE_KIND>N</TYPE_KIND>
     <LENGTH>4</LENGTH>
     <IS_KEY>X</IS_KEY>
    </item>
    <item>
     <POS>5</POS>
     <NAME>SCR_A_SSCR</NAME>
     <TYPE_KIND>C</TYPE_KIND>
     <LENGTH>30</LENGTH>
     <IS_KEY>X</IS_KEY>
    </item>
    <item>
     <POS>6</POS>
     <NAME>SCR_TEXT</NAME>
     <TYPE_KIND>C</TYPE_KIND>
     <LENGTH>60</LENGTH>
    </item>
   </SXS_SCRNT_field_catalog>
   <SXS_TABLET_field_catalog>
    <item>
     <POS>1</POS>
     <NAME>EXIT_NAME</NAME>
     <TYPE_KIND>C</TYPE_KIND>
     <LENGTH>20</LENGTH>
     <IS_KEY>X</IS_KEY>
    </item>
    <item>
     <POS>2</POS>
     <NAME>SPRSL</NAME>
     <TYPE_KIND>C</TYPE_KIND>
     <LENGTH>1</LENGTH>
     <IS_KEY>X</IS_KEY>
    </item>
    <item>
     <POS>3</POS>
     <NAME>TABNAME</NAME>
     <TYPE_KIND>C</TYPE_KIND>
     <LENGTH>30</LENGTH>
     <IS_KEY>X</IS_KEY>
    </item>
    <item>
     <POS>4</POS>
     <NAME>TEXT</NAME>
     <TYPE_KIND>C</TYPE_KIND>
     <LENGTH>60</LENGTH>
    </item>
   </SXS_TABLET_field_catalog>
   <SXS_FCODET_field_catalog>
    <item>
     <POS>1</POS>
     <NAME>EXIT_NAME</NAME>
     <TYPE_KIND>C</TYPE_KIND>
     <LENGTH>20</LENGTH>
     <IS_KEY>X</IS_KEY>
    </item>
    <item>
     <POS>2</POS>
     <NAME>SPRSL</NAME>
     <TYPE_KIND>C</TYPE_KIND>
     <LENGTH>1</LENGTH>
     <IS_KEY>X</IS_KEY>
    </item>
    <item>
     <POS>3</POS>
     <NAME>GUI_PROG</NAME>
     <TYPE_KIND>C</TYPE_KIND>
     <LENGTH>40</LENGTH>
     <IS_KEY>X</IS_KEY>
    </item>
    <item>
     <POS>4</POS>
     <NAME>GUI_CODE</NAME>
     <TYPE_KIND>C</TYPE_KIND>
     <LENGTH>20</LENGTH>
     <IS_KEY>X</IS_KEY>
    </item>
    <item>
     <POS>5</POS>
     <NAME>GUI_TEXT</NAME>
     <TYPE_KIND>C</TYPE_KIND>
     <LENGTH>60</LENGTH>
    </item>
   </SXS_FCODET_field_catalog>
  </asx:values>
 </asx:abap>
</abapGit>
